{
    "theorem": "caofrss",
    "hyps": [
        [
            1,
            2
        ],
        [
            1,
            20
        ],
        [
            1,
            32
        ],
        [
            2,
            3
        ],
        [
            3,
            4
        ],
        [
            3,
            7
        ],
        [
            3,
            10
        ],
        [
            3,
            13
        ],
        [
            4,
            5
        ],
        [
            4,
            6
        ],
        [
            7,
            8
        ],
        [
            7,
            9
        ],
        [
            10,
            11
        ],
        [
            11,
            12
        ],
        [
            13,
            14
        ],
        [
            13,
            17
        ],
        [
            14,
            15
        ],
        [
            14,
            16
        ],
        [
            17,
            18
        ],
        [
            17,
            19
        ],
        [
            20,
            21
        ],
        [
            20,
            24
        ],
        [
            20,
            27
        ],
        [
            20,
            28
        ],
        [
            20,
            29
        ],
        [
            20,
            30
        ],
        [
            20,
            31
        ],
        [
            21,
            22
        ],
        [
            21,
            23
        ],
        [
            24,
            25
        ],
        [
            24,
            26
        ],
        [
            32,
            33
        ],
        [
            32,
            36
        ],
        [
            32,
            39
        ],
        [
            32,
            40
        ],
        [
            32,
            41
        ],
        [
            32,
            42
        ],
        [
            32,
            43
        ],
        [
            33,
            34
        ],
        [
            33,
            35
        ],
        [
            36,
            37
        ],
        [
            36,
            38
        ]
    ],
    "expression": "( \ud835\udf11 \u2192 ( F oR R G \u2192 F oR T G ) )",
    "steps": [
        {
            "expression": "\u22a2 ( \ud835\udf11 \u2192 ( F oR R G \u2192 F oR T G ) )",
            "prop_expression": "( \ud835\udf11 \u2192 ( \ud835\udf13 \u2192 \ud835\udf12 ) ), ( \ud835\udf11 \u2192 ( \ud835\udf03 \u2194 \ud835\udf13 ) ), ( \ud835\udf11 \u2192 ( \ud835\udf0f \u2194 \ud835\udf12 ) ) \u22a2 ( \ud835\udf11 \u2192 ( \ud835\udf03 \u2192 \ud835\udf0f ) )",
            "step": 1,
            "theorem": "3imtr4d",
            "ground_truth": "3imtr4d \u22a2 ( \ud835\udf11 \u2192 ( F oR R G \u2192 F oR T G ) )",
            "ground_truth_display": false,
            "statement_depth": 0,
            "_thrs_random_uniform": 0.42383,
            "_thrs_reconstruct": 0.0,
            "_thrs_obviousness": 1.0,
            "_thrs_weight": 0.84375,
            "_thrs_complexity": 0.5,
            "_thrs_surprisingness": 0.40529,
            "_thrs_intensity": 1.0,
            "_thrs_interestingness": 0.74981,
            "_thrs_logistic_regression": 0.99922,
            "_thrs_random_forest": 0.94
        },
        {
            "expression": "\u22a2 ( \ud835\udf11 \u2192 ( \u2200 w \u2208 A ( F ` w ) R ( G ` w ) \u2192 \u2200 w \u2208 A ( F ` w ) T ( G ` w ) ) )",
            "prop_expression": "( ( \ud835\udf11 \u2227 x \u2208 A ) \u2192 ( \ud835\udf13 \u2192 \ud835\udf12 ) ) \u22a2 ( \ud835\udf11 \u2192 ( \u2200 x \u2208 A \ud835\udf13 \u2192 \u2200 x \u2208 A \ud835\udf12 ) )",
            "step": 2,
            "theorem": "ralimdva",
            "ground_truth": "ralimdva \u22a2 ( \ud835\udf11 \u2192 ( \u2200 w \u2208 A ( F ` w ) R ( G ` w ) \u2192 \u2200 w \u2208 A ( F ` w ) T ( G ` w ) ) )",
            "ground_truth_display": false,
            "statement_depth": 0,
            "_thrs_random_uniform": 0.17374,
            "_thrs_reconstruct": 0.0,
            "_thrs_obviousness": 0.16395,
            "_thrs_weight": 0.46875,
            "_thrs_complexity": 0.125,
            "_thrs_surprisingness": 1.0,
            "_thrs_intensity": 0.15939,
            "_thrs_interestingness": 0.38342,
            "_thrs_logistic_regression": 0.96866,
            "_thrs_random_forest": 0.94
        },
        {
            "expression": "\u22a2 ( ( \ud835\udf11 \u2227 w \u2208 A ) \u2192 ( ( F ` w ) R ( G ` w ) \u2192 ( F ` w ) T ( G ` w ) ) )",
            "prop_expression": "( \ud835\udf11 \u2192 \ud835\udf13 ), ( \ud835\udf11 \u2192 \ud835\udf12 ), ( \ud835\udf11 \u2192 \ud835\udf03 ), ( ( ( \ud835\udf13 \u2227 \ud835\udf12 ) \u2227 \ud835\udf03 ) \u2192 \ud835\udf0f ) \u22a2 ( \ud835\udf11 \u2192 \ud835\udf0f )",
            "step": 3,
            "theorem": "syl21anc",
            "ground_truth": "syl21anc \u22a2 ( ( \ud835\udf11 \u2227 w \u2208 A ) \u2192 ( ( F ` w ) R ( G ` w ) \u2192 ( F ` w ) T ( G ` w ) ) )",
            "ground_truth_display": false,
            "statement_depth": 0,
            "_thrs_random_uniform": 0.82055,
            "_thrs_reconstruct": 0.0,
            "_thrs_obviousness": 0.16395,
            "_thrs_weight": 0.5625,
            "_thrs_complexity": 0.125,
            "_thrs_surprisingness": 1.0,
            "_thrs_intensity": 0.84022,
            "_thrs_interestingness": 0.53833,
            "_thrs_logistic_regression": 0.99925,
            "_thrs_random_forest": 0.8
        },
        {
            "expression": "\u22a2 ( ( \ud835\udf11 \u2227 w \u2208 A ) \u2192 ( F ` w ) \u2208 S )",
            "prop_expression": "( \ud835\udf11 \u2192 \ud835\udf13 ), ( ( \ud835\udf13 \u2227 \ud835\udf12 ) \u2192 \ud835\udf03 ) \u22a2 ( ( \ud835\udf11 \u2227 \ud835\udf12 ) \u2192 \ud835\udf03 )",
            "step": 4,
            "theorem": "sylan",
            "ground_truth": "sylan \u22a2 ( ( \ud835\udf11 \u2227 w \u2208 A ) \u2192 ( F ` w ) \u2208 S )",
            "ground_truth_display": false,
            "statement_depth": 0,
            "_thrs_random_uniform": 0.65218,
            "_thrs_reconstruct": 0.0,
            "_thrs_obviousness": 0.08184,
            "_thrs_weight": 0.84375,
            "_thrs_complexity": 0.375,
            "_thrs_surprisingness": 0.47953,
            "_thrs_intensity": 0.42241,
            "_thrs_interestingness": 0.4405,
            "_thrs_logistic_regression": 0.99052,
            "_thrs_random_forest": 0.88
        },
        {
            "expression": "\u22a2 ( \ud835\udf11 \u2192 F : A -\u2192 S )",
            "prop_expression": " \u22a2 ( \ud835\udf11 \u2192 F : A -\u2192 S )",
            "step": 5,
            "theorem": "caofref.2",
            "ground_truth": "caofref.2 \u22a2 ( \ud835\udf11 \u2192 F : A -\u2192 S )",
            "ground_truth_display": false,
            "statement_depth": 0,
            "_thrs_random_uniform": 0.63144,
            "_thrs_reconstruct": 0.0,
            "_thrs_obviousness": 0.0,
            "_thrs_weight": 0.96875,
            "_thrs_complexity": 0.625,
            "_thrs_surprisingness": 0.2461,
            "_thrs_intensity": 0.20661,
            "_thrs_interestingness": 0.40929,
            "_thrs_logistic_regression": 0.93445,
            "_thrs_random_forest": 0.97
        },
        {
            "expression": "\u22a2 ( ( F : A -\u2192 S \u2227 w \u2208 A ) \u2192 ( F ` w ) \u2208 S )",
            "prop_expression": " \u22a2 ( ( F : A -\u2192 B \u2227 C \u2208 A ) \u2192 ( F ` C ) \u2208 B )",
            "step": 6,
            "theorem": "ffvelrn",
            "ground_truth": "ffvelrn \u22a2 ( ( F : A -\u2192 S \u2227 w \u2208 A ) \u2192 ( F ` w ) \u2208 S )",
            "ground_truth_display": false,
            "statement_depth": 0,
            "_thrs_random_uniform": 0.51389,
            "_thrs_reconstruct": 0.19577,
            "_thrs_obviousness": 0.08184,
            "_thrs_weight": 0.75,
            "_thrs_complexity": 0.375,
            "_thrs_surprisingness": 0.47387,
            "_thrs_intensity": 0.06887,
            "_thrs_interestingness": 0.34991,
            "_thrs_logistic_regression": 0.93463,
            "_thrs_random_forest": 0.89625
        },
        {
            "expression": "\u22a2 ( ( \ud835\udf11 \u2227 w \u2208 A ) \u2192 ( G ` w ) \u2208 S )",
            "prop_expression": "( \ud835\udf11 \u2192 \ud835\udf13 ), ( ( \ud835\udf13 \u2227 \ud835\udf12 ) \u2192 \ud835\udf03 ) \u22a2 ( ( \ud835\udf11 \u2227 \ud835\udf12 ) \u2192 \ud835\udf03 )",
            "step": 7,
            "theorem": "sylan",
            "ground_truth": "sylan \u22a2 ( ( \ud835\udf11 \u2227 w \u2208 A ) \u2192 ( G ` w ) \u2208 S )",
            "ground_truth_display": false,
            "statement_depth": 0,
            "_thrs_random_uniform": 0.34771,
            "_thrs_reconstruct": 0.0,
            "_thrs_obviousness": 0.08184,
            "_thrs_weight": 0.84375,
            "_thrs_complexity": 0.375,
            "_thrs_surprisingness": 0.48117,
            "_thrs_intensity": 0.42241,
            "_thrs_interestingness": 0.44083,
            "_thrs_logistic_regression": 0.9905,
            "_thrs_random_forest": 0.88
        },
        {
            "expression": "\u22a2 ( \ud835\udf11 \u2192 G : A -\u2192 S )",
            "prop_expression": " \u22a2 ( \ud835\udf11 \u2192 G : A -\u2192 S )",
            "step": 8,
            "theorem": "caofcom.3",
            "ground_truth": "caofcom.3 \u22a2 ( \ud835\udf11 \u2192 G : A -\u2192 S )",
            "ground_truth_display": false,
            "statement_depth": 0,
            "_thrs_random_uniform": 0.35106,
            "_thrs_reconstruct": 0.0,
            "_thrs_obviousness": 0.0,
            "_thrs_weight": 0.96875,
            "_thrs_complexity": 0.625,
            "_thrs_surprisingness": 0.23943,
            "_thrs_intensity": 0.20661,
            "_thrs_interestingness": 0.40796,
            "_thrs_logistic_regression": 0.935,
            "_thrs_random_forest": 0.97
        },
        {
            "expression": "\u22a2 ( ( G : A -\u2192 S \u2227 w \u2208 A ) \u2192 ( G ` w ) \u2208 S )",
            "prop_expression": " \u22a2 ( ( F : A -\u2192 B \u2227 C \u2208 A ) \u2192 ( F ` C ) \u2208 B )",
            "step": 9,
            "theorem": "ffvelrn",
            "ground_truth": "ffvelrn \u22a2 ( ( G : A -\u2192 S \u2227 w \u2208 A ) \u2192 ( G ` w ) \u2208 S )",
            "ground_truth_display": false,
            "statement_depth": 0,
            "_thrs_random_uniform": 0.01136,
            "_thrs_reconstruct": 0.19577,
            "_thrs_obviousness": 0.08184,
            "_thrs_weight": 0.75,
            "_thrs_complexity": 0.375,
            "_thrs_surprisingness": 0.47451,
            "_thrs_intensity": 0.06887,
            "_thrs_interestingness": 0.35004,
            "_thrs_logistic_regression": 0.93458,
            "_thrs_random_forest": 0.89625
        },
        {
            "expression": "\u22a2 ( ( \ud835\udf11 \u2227 w \u2208 A ) \u2192 \u2200 x \u2208 S \u2200 y \u2208 S ( x R y \u2192 x T y ) )",
            "prop_expression": "( \ud835\udf11 \u2192 \ud835\udf13 ) \u22a2 ( ( \ud835\udf11 \u2227 \ud835\udf12 ) \u2192 \ud835\udf13 )",
            "step": 10,
            "theorem": "adantr",
            "ground_truth": "adantr \u22a2 ( ( \ud835\udf11 \u2227 w \u2208 A ) \u2192 \u2200 x \u2208 S \u2200 y \u2208 S ( x R y \u2192 x T y ) )",
            "ground_truth_display": false,
            "statement_depth": 0,
            "_thrs_random_uniform": 0.22046,
            "_thrs_reconstruct": 0.0,
            "_thrs_obviousness": 0.0,
            "_thrs_weight": 0.625,
            "_thrs_complexity": 0.125,
            "_thrs_surprisingness": 0.46794,
            "_thrs_intensity": 0.22137,
            "_thrs_interestingness": 0.28786,
            "_thrs_logistic_regression": 0.99052,
            "_thrs_random_forest": 0.795
        },
        {
            "expression": "\u22a2 ( \ud835\udf11 \u2192 \u2200 x \u2208 S \u2200 y \u2208 S ( x R y \u2192 x T y ) )",
            "prop_expression": "( ( \ud835\udf11 \u2227 ( x \u2208 A \u2227 y \u2208 B ) ) \u2192 \ud835\udf13 ) \u22a2 ( \ud835\udf11 \u2192 \u2200 x \u2208 A \u2200 y \u2208 B \ud835\udf13 )",
            "step": 11,
            "theorem": "ralrimivva",
            "ground_truth": "ralrimivva \u22a2 ( \ud835\udf11 \u2192 \u2200 x \u2208 S \u2200 y \u2208 S ( x R y \u2192 x T y ) )",
            "ground_truth_display": false,
            "statement_depth": 0,
            "_thrs_random_uniform": 0.33253,
            "_thrs_reconstruct": 0.0,
            "_thrs_obviousness": 0.0,
            "_thrs_weight": 0.71875,
            "_thrs_complexity": 0.375,
            "_thrs_surprisingness": 0.39263,
            "_thrs_intensity": 0.20661,
            "_thrs_interestingness": 0.3386,
            "_thrs_logistic_regression": 0.97042,
            "_thrs_random_forest": 0.735
        },
        {
            "expression": "\u22a2 ( ( \ud835\udf11 \u2227 ( x \u2208 S \u2227 y \u2208 S ) ) \u2192 ( x R y \u2192 x T y ) )",
            "prop_expression": " \u22a2 ( ( \ud835\udf11 \u2227 ( x \u2208 S \u2227 y \u2208 S ) ) \u2192 ( x R y \u2192 x T y ) )",
            "step": 12,
            "theorem": "caofrss.4",
            "ground_truth": "caofrss.4 \u22a2 ( ( \ud835\udf11 \u2227 ( x \u2208 S \u2227 y \u2208 S ) ) \u2192 ( x R y \u2192 x T y ) )",
            "ground_truth_display": false,
            "statement_depth": 0,
            "_thrs_random_uniform": 0.25523,
            "_thrs_reconstruct": 0.0,
            "_thrs_obviousness": 0.0,
            "_thrs_weight": 0.71875,
            "_thrs_complexity": 0.375,
            "_thrs_surprisingness": 0.39263,
            "_thrs_intensity": 0.05404,
            "_thrs_interestingness": 0.30808,
            "_thrs_logistic_regression": 0.93507,
            "_thrs_random_forest": 0.78
        },
        {
            "expression": "\u22a2 ( ( ( ( F ` w ) \u2208 S \u2227 ( G ` w ) \u2208 S ) \u2227 \u2200 x \u2208 S \u2200 y \u2208 S ( x R y \u2192 x T y ) ) \u2192 ( ( F ` w ) R ( G ` w ) \u2192 ( F ` w ) T ( G ` w ) ) )",
            "prop_expression": "( x = A \u2192 ( \ud835\udf11 \u2194 \ud835\udf12 ) ), ( y = B \u2192 ( \ud835\udf12 \u2194 \ud835\udf13 ) ) \u22a2 ( ( ( A \u2208 C \u2227 B \u2208 D ) \u2227 \u2200 x \u2208 C \u2200 y \u2208 D \ud835\udf11 ) \u2192 \ud835\udf13 )",
            "step": 13,
            "theorem": "rcla42va",
            "ground_truth": "rcla42va \u22a2 ( ( ( ( F ` w ) \u2208 S \u2227 ( G ` w ) \u2208 S ) \u2227 \u2200 x \u2208 S \u2200 y \u2208 S ( x R y \u2192 x T y ) ) \u2192 ( ( F ` w ) R ( G ` w ) \u2192 ( F ` w ) T ( G ` w ) ) )",
            "ground_truth_display": false,
            "statement_depth": 0,
            "_thrs_random_uniform": 0.27447,
            "_thrs_reconstruct": 0.0,
            "_thrs_obviousness": 0.00028,
            "_thrs_weight": 0.0,
            "_thrs_complexity": 0.0,
            "_thrs_surprisingness": 0.85251,
            "_thrs_intensity": 0.427,
            "_thrs_interestingness": 0.25596,
            "_thrs_logistic_regression": 0.99492,
            "_thrs_random_forest": 0.615
        },
        {
            "expression": "\u22a2 ( x = ( F ` w ) \u2192 ( ( x R y \u2192 x T y ) \u2194 ( ( F ` w ) R y \u2192 ( F ` w ) T y ) ) )",
            "prop_expression": "( \ud835\udf11 \u2192 ( \ud835\udf13 \u2194 \ud835\udf12 ) ), ( \ud835\udf11 \u2192 ( \ud835\udf03 \u2194 \ud835\udf0f ) ) \u22a2 ( \ud835\udf11 \u2192 ( ( \ud835\udf13 \u2192 \ud835\udf03 ) \u2194 ( \ud835\udf12 \u2192 \ud835\udf0f ) ) )",
            "step": 14,
            "theorem": "imbi12d",
            "ground_truth": "imbi12d \u22a2 ( x = ( F ` w ) \u2192 ( ( x R y \u2192 x T y ) \u2194 ( ( F ` w ) R y \u2192 ( F ` w ) T y ) ) )",
            "ground_truth_display": false,
            "statement_depth": 0,
            "_thrs_random_uniform": 0.30159,
            "_thrs_reconstruct": 0.0,
            "_thrs_obviousness": 0.00014,
            "_thrs_weight": 0.5,
            "_thrs_complexity": 0.375,
            "_thrs_surprisingness": 0.19698,
            "_thrs_intensity": 0.27273,
            "_thrs_interestingness": 0.26897,
            "_thrs_logistic_regression": 0.98023,
            "_thrs_random_forest": 0.56
        },
        {
            "expression": "\u22a2 ( x = ( F ` w ) \u2192 ( x R y \u2194 ( F ` w ) R y ) )",
            "prop_expression": " \u22a2 ( A = B \u2192 ( A R C \u2194 B R C ) )",
            "step": 15,
            "theorem": "breq1",
            "ground_truth": "breq1 \u22a2 ( x = ( F ` w ) \u2192 ( x R y \u2194 ( F ` w ) R y ) )",
            "ground_truth_display": false,
            "statement_depth": 0,
            "_thrs_random_uniform": 0.14811,
            "_thrs_reconstruct": 0.00016,
            "_thrs_obviousness": 7e-05,
            "_thrs_weight": 0.75,
            "_thrs_complexity": 0.5,
            "_thrs_surprisingness": 0.06763,
            "_thrs_intensity": 0.04132,
            "_thrs_interestingness": 0.2718,
            "_thrs_logistic_regression": 0.91935,
            "_thrs_random_forest": 0.715
        },
        {
            "expression": "\u22a2 ( x = ( F ` w ) \u2192 ( x T y \u2194 ( F ` w ) T y ) )",
            "prop_expression": " \u22a2 ( A = B \u2192 ( A R C \u2194 B R C ) )",
            "step": 16,
            "theorem": "breq1",
            "ground_truth": "breq1 \u22a2 ( x = ( F ` w ) \u2192 ( x T y \u2194 ( F ` w ) T y ) )",
            "ground_truth_display": false,
            "statement_depth": 0,
            "_thrs_random_uniform": 0.3346,
            "_thrs_reconstruct": 0.00016,
            "_thrs_obviousness": 7e-05,
            "_thrs_weight": 0.75,
            "_thrs_complexity": 0.5,
            "_thrs_surprisingness": 0.06763,
            "_thrs_intensity": 0.04132,
            "_thrs_interestingness": 0.2718,
            "_thrs_logistic_regression": 0.91935,
            "_thrs_random_forest": 0.715
        },
        {
            "expression": "\u22a2 ( y = ( G ` w ) \u2192 ( ( ( F ` w ) R y \u2192 ( F ` w ) T y ) \u2194 ( ( F ` w ) R ( G ` w ) \u2192 ( F ` w ) T ( G ` w ) ) ) )",
            "prop_expression": "( \ud835\udf11 \u2192 ( \ud835\udf13 \u2194 \ud835\udf12 ) ), ( \ud835\udf11 \u2192 ( \ud835\udf03 \u2194 \ud835\udf0f ) ) \u22a2 ( \ud835\udf11 \u2192 ( ( \ud835\udf13 \u2192 \ud835\udf03 ) \u2194 ( \ud835\udf12 \u2192 \ud835\udf0f ) ) )",
            "step": 17,
            "theorem": "imbi12d",
            "ground_truth": "imbi12d \u22a2 ( y = ( G ` w ) \u2192 ( ( ( F ` w ) R y \u2192 ( F ` w ) T y ) \u2194 ( ( F ` w ) R ( G ` w ) \u2192 ( F ` w ) T ( G ` w ) ) ) )",
            "ground_truth_display": false,
            "statement_depth": 0,
            "_thrs_random_uniform": 0.84477,
            "_thrs_reconstruct": 0.0,
            "_thrs_obviousness": 0.00014,
            "_thrs_weight": 0.25,
            "_thrs_complexity": 0.375,
            "_thrs_surprisingness": 0.37544,
            "_thrs_intensity": 0.25384,
            "_thrs_interestingness": 0.25088,
            "_thrs_logistic_regression": 0.96516,
            "_thrs_random_forest": 0.565
        },
        {
            "expression": "\u22a2 ( y = ( G ` w ) \u2192 ( ( F ` w ) R y \u2194 ( F ` w ) R ( G ` w ) ) )",
            "prop_expression": " \u22a2 ( A = B \u2192 ( C R A \u2194 C R B ) )",
            "step": 18,
            "theorem": "breq2",
            "ground_truth": "breq2 \u22a2 ( y = ( G ` w ) \u2192 ( ( F ` w ) R y \u2194 ( F ` w ) R ( G ` w ) ) )",
            "ground_truth_display": false,
            "statement_depth": 0,
            "_thrs_random_uniform": 0.88609,
            "_thrs_reconstruct": 0.00017,
            "_thrs_obviousness": 7e-05,
            "_thrs_weight": 0.625,
            "_thrs_complexity": 0.5,
            "_thrs_surprisingness": 0.19798,
            "_thrs_intensity": 0.0,
            "_thrs_interestingness": 0.26461,
            "_thrs_logistic_regression": 0.87156,
            "_thrs_random_forest": 0.525
        },
        {
            "expression": "\u22a2 ( y = ( G ` w ) \u2192 ( ( F ` w ) T y \u2194 ( F ` w ) T ( G ` w ) ) )",
            "prop_expression": " \u22a2 ( A = B \u2192 ( C R A \u2194 C R B ) )",
            "step": 19,
            "theorem": "breq2",
            "ground_truth": "breq2 \u22a2 ( y = ( G ` w ) \u2192 ( ( F ` w ) T y \u2194 ( F ` w ) T ( G ` w ) ) )",
            "ground_truth_display": false,
            "statement_depth": 0,
            "_thrs_random_uniform": 0.42869,
            "_thrs_reconstruct": 0.00017,
            "_thrs_obviousness": 7e-05,
            "_thrs_weight": 0.625,
            "_thrs_complexity": 0.5,
            "_thrs_surprisingness": 0.19798,
            "_thrs_intensity": 0.0,
            "_thrs_interestingness": 0.26461,
            "_thrs_logistic_regression": 0.87156,
            "_thrs_random_forest": 0.525
        },
        {
            "expression": "\u22a2 ( \ud835\udf11 \u2192 ( F oR R G \u2194 \u2200 w \u2208 A ( F ` w ) R ( G ` w ) ) )",
            "prop_expression": "( \ud835\udf11 \u2192 F Fn A ), ( \ud835\udf11 \u2192 G Fn B ), ( \ud835\udf11 \u2192 A \u2208 V ), ( \ud835\udf11 \u2192 B \u2208 W ), ( A \u2229 B ) = S, ( ( \ud835\udf11 \u2227 x \u2208 A ) \u2192 ( F ` x ) = C ), ( ( \ud835\udf11 \u2227 x \u2208 B ) \u2192 ( G ` x ) = D ) \u22a2 ( \ud835\udf11 \u2192 ( F oR R G \u2194 \u2200 x \u2208 S C R D ) )",
            "step": 20,
            "theorem": "ofrfval",
            "ground_truth": "ofrfval \u22a2 ( \ud835\udf11 \u2192 ( F oR R G \u2194 \u2200 w \u2208 A ( F ` w ) R ( G ` w ) ) )",
            "ground_truth_display": false,
            "statement_depth": 0,
            "_thrs_random_uniform": 0.61734,
            "_thrs_reconstruct": 1.0,
            "_thrs_obviousness": 0.41802,
            "_thrs_weight": 0.65625,
            "_thrs_complexity": 0.125,
            "_thrs_surprisingness": 0.72469,
            "_thrs_intensity": 0.66942,
            "_thrs_interestingness": 0.51868,
            "_thrs_logistic_regression": 0.99879,
            "_thrs_random_forest": 0.945
        },
        {
            "expression": "\u22a2 ( \ud835\udf11 \u2192 F Fn A )",
            "prop_expression": "( \ud835\udf11 \u2192 \ud835\udf13 ), ( \ud835\udf13 \u2192 \ud835\udf12 ) \u22a2 ( \ud835\udf11 \u2192 \ud835\udf12 )",
            "step": 21,
            "theorem": "syl",
            "ground_truth": "syl \u22a2 ( \ud835\udf11 \u2192 F Fn A )",
            "ground_truth_display": false,
            "statement_depth": 0,
            "_thrs_random_uniform": 0.22013,
            "_thrs_reconstruct": 0.0,
            "_thrs_obviousness": 0.0,
            "_thrs_weight": 1.0,
            "_thrs_complexity": 0.75,
            "_thrs_surprisingness": 0.13765,
            "_thrs_intensity": 0.53719,
            "_thrs_interestingness": 0.48497,
            "_thrs_logistic_regression": 0.9817,
            "_thrs_random_forest": 0.93
        },
        {
            "expression": "\u22a2 ( \ud835\udf11 \u2192 F : A -\u2192 S )",
            "prop_expression": " \u22a2 ( \ud835\udf11 \u2192 F : A -\u2192 S )",
            "step": 22,
            "theorem": "caofref.2",
            "ground_truth": "caofref.2 \u22a2 ( \ud835\udf11 \u2192 F : A -\u2192 S )",
            "ground_truth_display": false,
            "statement_depth": 0,
            "_thrs_random_uniform": 0.32784,
            "_thrs_reconstruct": 0.0,
            "_thrs_obviousness": 0.0,
            "_thrs_weight": 0.96875,
            "_thrs_complexity": 0.625,
            "_thrs_surprisingness": 0.2461,
            "_thrs_intensity": 0.20661,
            "_thrs_interestingness": 0.40929,
            "_thrs_logistic_regression": 0.93445,
            "_thrs_random_forest": 1.0
        },
        {
            "expression": "\u22a2 ( F : A -\u2192 S \u2192 F Fn A )",
            "prop_expression": " \u22a2 ( F : A -\u2192 B \u2192 F Fn A )",
            "step": 23,
            "theorem": "ffn",
            "ground_truth": "ffn \u22a2 ( F : A -\u2192 S \u2192 F Fn A )",
            "ground_truth_display": false,
            "statement_depth": 0,
            "_thrs_random_uniform": 0.02069,
            "_thrs_reconstruct": 0.0,
            "_thrs_obviousness": 0.0,
            "_thrs_weight": 0.90625,
            "_thrs_complexity": 0.625,
            "_thrs_surprisingness": 0.27178,
            "_thrs_intensity": 0.11216,
            "_thrs_interestingness": 0.38304,
            "_thrs_logistic_regression": 0.88626,
            "_thrs_random_forest": 0.985
        },
        {
            "expression": "\u22a2 ( \ud835\udf11 \u2192 G Fn A )",
            "prop_expression": "( \ud835\udf11 \u2192 \ud835\udf13 ), ( \ud835\udf13 \u2192 \ud835\udf12 ) \u22a2 ( \ud835\udf11 \u2192 \ud835\udf12 )",
            "step": 24,
            "theorem": "syl",
            "ground_truth": "syl \u22a2 ( \ud835\udf11 \u2192 G Fn A )",
            "ground_truth_display": false,
            "statement_depth": 0,
            "_thrs_random_uniform": 0.84675,
            "_thrs_reconstruct": 0.0,
            "_thrs_obviousness": 0.0,
            "_thrs_weight": 1.0,
            "_thrs_complexity": 0.75,
            "_thrs_surprisingness": 0.13386,
            "_thrs_intensity": 0.53719,
            "_thrs_interestingness": 0.48421,
            "_thrs_logistic_regression": 0.98179,
            "_thrs_random_forest": 0.93
        },
        {
            "expression": "\u22a2 ( \ud835\udf11 \u2192 G : A -\u2192 S )",
            "prop_expression": " \u22a2 ( \ud835\udf11 \u2192 G : A -\u2192 S )",
            "step": 25,
            "theorem": "caofcom.3",
            "ground_truth": "caofcom.3 \u22a2 ( \ud835\udf11 \u2192 G : A -\u2192 S )",
            "ground_truth_display": false,
            "statement_depth": 0,
            "_thrs_random_uniform": 0.86564,
            "_thrs_reconstruct": 0.0,
            "_thrs_obviousness": 0.0,
            "_thrs_weight": 0.96875,
            "_thrs_complexity": 0.625,
            "_thrs_surprisingness": 0.23943,
            "_thrs_intensity": 0.20661,
            "_thrs_interestingness": 0.40796,
            "_thrs_logistic_regression": 0.935,
            "_thrs_random_forest": 1.0
        },
        {
            "expression": "\u22a2 ( G : A -\u2192 S \u2192 G Fn A )",
            "prop_expression": " \u22a2 ( F : A -\u2192 B \u2192 F Fn A )",
            "step": 26,
            "theorem": "ffn",
            "ground_truth": "ffn \u22a2 ( G : A -\u2192 S \u2192 G Fn A )",
            "ground_truth_display": false,
            "statement_depth": 0,
            "_thrs_random_uniform": 0.55582,
            "_thrs_reconstruct": 0.0,
            "_thrs_obviousness": 0.0,
            "_thrs_weight": 0.90625,
            "_thrs_complexity": 0.625,
            "_thrs_surprisingness": 0.26505,
            "_thrs_intensity": 0.11216,
            "_thrs_interestingness": 0.38169,
            "_thrs_logistic_regression": 0.88718,
            "_thrs_random_forest": 0.985
        },
        {
            "expression": "\u22a2 ( \ud835\udf11 \u2192 A \u2208 V )",
            "prop_expression": " \u22a2 ( \ud835\udf11 \u2192 A \u2208 V )",
            "step": 27,
            "theorem": "caofref.1",
            "ground_truth": "caofref.1 \u22a2 ( \ud835\udf11 \u2192 A \u2208 V )",
            "ground_truth_display": false,
            "statement_depth": 0,
            "_thrs_random_uniform": 0.0171,
            "_thrs_reconstruct": 0.0,
            "_thrs_obviousness": 0.0,
            "_thrs_weight": 1.0,
            "_thrs_complexity": 0.75,
            "_thrs_surprisingness": 0.14202,
            "_thrs_intensity": 0.20661,
            "_thrs_interestingness": 0.41973,
            "_thrs_logistic_regression": 0.8996,
            "_thrs_random_forest": 0.96
        },
        {
            "expression": "\u22a2 ( \ud835\udf11 \u2192 A \u2208 V )",
            "prop_expression": " \u22a2 ( \ud835\udf11 \u2192 A \u2208 V )",
            "step": 28,
            "theorem": "caofref.1",
            "ground_truth": "caofref.1 \u22a2 ( \ud835\udf11 \u2192 A \u2208 V )",
            "ground_truth_display": false,
            "statement_depth": 0,
            "_thrs_random_uniform": 0.14723,
            "_thrs_reconstruct": 0.0,
            "_thrs_obviousness": 0.0,
            "_thrs_weight": 1.0,
            "_thrs_complexity": 0.75,
            "_thrs_surprisingness": 0.14202,
            "_thrs_intensity": 0.20661,
            "_thrs_interestingness": 0.41973,
            "_thrs_logistic_regression": 0.8996,
            "_thrs_random_forest": 0.96
        },
        {
            "expression": "\u22a2 ( A \u2229 A ) = A",
            "prop_expression": " \u22a2 ( A \u2229 A ) = A",
            "step": 29,
            "theorem": "inidm",
            "ground_truth": "inidm \u22a2 ( A \u2229 A ) = A",
            "ground_truth_display": false,
            "statement_depth": 0,
            "_thrs_random_uniform": 0.45095,
            "_thrs_reconstruct": 0.0,
            "_thrs_obviousness": 0.0,
            "_thrs_weight": 1.0,
            "_thrs_complexity": 1.0,
            "_thrs_surprisingness": 0.0,
            "_thrs_intensity": 0.04132,
            "_thrs_interestingness": 0.40826,
            "_thrs_logistic_regression": 0.55551,
            "_thrs_random_forest": 0.915
        },
        {
            "expression": "\u22a2 ( ( \ud835\udf11 \u2227 w \u2208 A ) \u2192 ( F ` w ) = ( F ` w ) )",
            "prop_expression": " \u22a2 ( \ud835\udf11 \u2192 A = A )",
            "step": 30,
            "theorem": "eqidd",
            "ground_truth": "eqidd \u22a2 ( ( \ud835\udf11 \u2227 w \u2208 A ) \u2192 ( F ` w ) = ( F ` w ) )",
            "ground_truth_display": false,
            "statement_depth": 0,
            "_thrs_random_uniform": 0.4623,
            "_thrs_reconstruct": 0.0,
            "_thrs_obviousness": 0.0,
            "_thrs_weight": 0.8125,
            "_thrs_complexity": 0.5,
            "_thrs_surprisingness": 0.29105,
            "_thrs_intensity": 0.07438,
            "_thrs_interestingness": 0.33559,
            "_thrs_logistic_regression": 0.91443,
            "_thrs_random_forest": 0.965
        },
        {
            "expression": "\u22a2 ( ( \ud835\udf11 \u2227 w \u2208 A ) \u2192 ( G ` w ) = ( G ` w ) )",
            "prop_expression": " \u22a2 ( \ud835\udf11 \u2192 A = A )",
            "step": 31,
            "theorem": "eqidd",
            "ground_truth": "eqidd \u22a2 ( ( \ud835\udf11 \u2227 w \u2208 A ) \u2192 ( G ` w ) = ( G ` w ) )",
            "ground_truth_display": false,
            "statement_depth": 0,
            "_thrs_random_uniform": 0.16339,
            "_thrs_reconstruct": 0.0,
            "_thrs_obviousness": 0.0,
            "_thrs_weight": 0.8125,
            "_thrs_complexity": 0.5,
            "_thrs_surprisingness": 0.29463,
            "_thrs_intensity": 0.07438,
            "_thrs_interestingness": 0.3363,
            "_thrs_logistic_regression": 0.91405,
            "_thrs_random_forest": 0.965
        },
        {
            "expression": "\u22a2 ( \ud835\udf11 \u2192 ( F oR T G \u2194 \u2200 w \u2208 A ( F ` w ) T ( G ` w ) ) )",
            "prop_expression": "( \ud835\udf11 \u2192 F Fn A ), ( \ud835\udf11 \u2192 G Fn B ), ( \ud835\udf11 \u2192 A \u2208 V ), ( \ud835\udf11 \u2192 B \u2208 W ), ( A \u2229 B ) = S, ( ( \ud835\udf11 \u2227 x \u2208 A ) \u2192 ( F ` x ) = C ), ( ( \ud835\udf11 \u2227 x \u2208 B ) \u2192 ( G ` x ) = D ) \u22a2 ( \ud835\udf11 \u2192 ( F oR R G \u2194 \u2200 x \u2208 S C R D ) )",
            "step": 32,
            "theorem": "ofrfval",
            "ground_truth": "ofrfval \u22a2 ( \ud835\udf11 \u2192 ( F oR T G \u2194 \u2200 w \u2208 A ( F ` w ) T ( G ` w ) ) )",
            "ground_truth_display": false,
            "statement_depth": 0,
            "_thrs_random_uniform": 0.21299,
            "_thrs_reconstruct": 1.0,
            "_thrs_obviousness": 0.41802,
            "_thrs_weight": 0.65625,
            "_thrs_complexity": 0.125,
            "_thrs_surprisingness": 0.72469,
            "_thrs_intensity": 0.66942,
            "_thrs_interestingness": 0.51868,
            "_thrs_logistic_regression": 0.99879,
            "_thrs_random_forest": 0.945
        },
        {
            "expression": "\u22a2 ( \ud835\udf11 \u2192 F Fn A )",
            "prop_expression": "( \ud835\udf11 \u2192 \ud835\udf13 ), ( \ud835\udf13 \u2192 \ud835\udf12 ) \u22a2 ( \ud835\udf11 \u2192 \ud835\udf12 )",
            "step": 33,
            "theorem": "syl",
            "ground_truth": "syl \u22a2 ( \ud835\udf11 \u2192 F Fn A )",
            "ground_truth_display": false,
            "statement_depth": 0,
            "_thrs_random_uniform": 0.89659,
            "_thrs_reconstruct": 0.0,
            "_thrs_obviousness": 0.0,
            "_thrs_weight": 1.0,
            "_thrs_complexity": 0.75,
            "_thrs_surprisingness": 0.13765,
            "_thrs_intensity": 0.53719,
            "_thrs_interestingness": 0.48497,
            "_thrs_logistic_regression": 0.9817,
            "_thrs_random_forest": 0.93
        },
        {
            "expression": "\u22a2 ( \ud835\udf11 \u2192 F : A -\u2192 S )",
            "prop_expression": " \u22a2 ( \ud835\udf11 \u2192 F : A -\u2192 S )",
            "step": 34,
            "theorem": "caofref.2",
            "ground_truth": "caofref.2 \u22a2 ( \ud835\udf11 \u2192 F : A -\u2192 S )",
            "ground_truth_display": false,
            "statement_depth": 0,
            "_thrs_random_uniform": 0.66111,
            "_thrs_reconstruct": 0.0,
            "_thrs_obviousness": 0.0,
            "_thrs_weight": 0.96875,
            "_thrs_complexity": 0.625,
            "_thrs_surprisingness": 0.2461,
            "_thrs_intensity": 0.20661,
            "_thrs_interestingness": 0.40929,
            "_thrs_logistic_regression": 0.93445,
            "_thrs_random_forest": 1.0
        },
        {
            "expression": "\u22a2 ( F : A -\u2192 S \u2192 F Fn A )",
            "prop_expression": " \u22a2 ( F : A -\u2192 B \u2192 F Fn A )",
            "step": 35,
            "theorem": "ffn",
            "ground_truth": "ffn \u22a2 ( F : A -\u2192 S \u2192 F Fn A )",
            "ground_truth_display": false,
            "statement_depth": 0,
            "_thrs_random_uniform": 0.67825,
            "_thrs_reconstruct": 0.0,
            "_thrs_obviousness": 0.0,
            "_thrs_weight": 0.90625,
            "_thrs_complexity": 0.625,
            "_thrs_surprisingness": 0.27178,
            "_thrs_intensity": 0.11216,
            "_thrs_interestingness": 0.38304,
            "_thrs_logistic_regression": 0.88626,
            "_thrs_random_forest": 0.985
        },
        {
            "expression": "\u22a2 ( \ud835\udf11 \u2192 G Fn A )",
            "prop_expression": "( \ud835\udf11 \u2192 \ud835\udf13 ), ( \ud835\udf13 \u2192 \ud835\udf12 ) \u22a2 ( \ud835\udf11 \u2192 \ud835\udf12 )",
            "step": 36,
            "theorem": "syl",
            "ground_truth": "syl \u22a2 ( \ud835\udf11 \u2192 G Fn A )",
            "ground_truth_display": false,
            "statement_depth": 0,
            "_thrs_random_uniform": 0.4722,
            "_thrs_reconstruct": 0.0,
            "_thrs_obviousness": 0.0,
            "_thrs_weight": 1.0,
            "_thrs_complexity": 0.75,
            "_thrs_surprisingness": 0.13386,
            "_thrs_intensity": 0.53719,
            "_thrs_interestingness": 0.48421,
            "_thrs_logistic_regression": 0.98179,
            "_thrs_random_forest": 0.93
        },
        {
            "expression": "\u22a2 ( \ud835\udf11 \u2192 G : A -\u2192 S )",
            "prop_expression": " \u22a2 ( \ud835\udf11 \u2192 G : A -\u2192 S )",
            "step": 37,
            "theorem": "caofcom.3",
            "ground_truth": "caofcom.3 \u22a2 ( \ud835\udf11 \u2192 G : A -\u2192 S )",
            "ground_truth_display": false,
            "statement_depth": 0,
            "_thrs_random_uniform": 0.21842,
            "_thrs_reconstruct": 0.0,
            "_thrs_obviousness": 0.0,
            "_thrs_weight": 0.96875,
            "_thrs_complexity": 0.625,
            "_thrs_surprisingness": 0.23943,
            "_thrs_intensity": 0.20661,
            "_thrs_interestingness": 0.40796,
            "_thrs_logistic_regression": 0.935,
            "_thrs_random_forest": 1.0
        },
        {
            "expression": "\u22a2 ( G : A -\u2192 S \u2192 G Fn A )",
            "prop_expression": " \u22a2 ( F : A -\u2192 B \u2192 F Fn A )",
            "step": 38,
            "theorem": "ffn",
            "ground_truth": "ffn \u22a2 ( G : A -\u2192 S \u2192 G Fn A )",
            "ground_truth_display": false,
            "statement_depth": 0,
            "_thrs_random_uniform": 0.7819,
            "_thrs_reconstruct": 0.0,
            "_thrs_obviousness": 0.0,
            "_thrs_weight": 0.90625,
            "_thrs_complexity": 0.625,
            "_thrs_surprisingness": 0.26505,
            "_thrs_intensity": 0.11216,
            "_thrs_interestingness": 0.38169,
            "_thrs_logistic_regression": 0.88718,
            "_thrs_random_forest": 0.985
        },
        {
            "expression": "\u22a2 ( \ud835\udf11 \u2192 A \u2208 V )",
            "prop_expression": " \u22a2 ( \ud835\udf11 \u2192 A \u2208 V )",
            "step": 39,
            "theorem": "caofref.1",
            "ground_truth": "caofref.1 \u22a2 ( \ud835\udf11 \u2192 A \u2208 V )",
            "ground_truth_display": false,
            "statement_depth": 0,
            "_thrs_random_uniform": 0.62875,
            "_thrs_reconstruct": 0.0,
            "_thrs_obviousness": 0.0,
            "_thrs_weight": 1.0,
            "_thrs_complexity": 0.75,
            "_thrs_surprisingness": 0.14202,
            "_thrs_intensity": 0.20661,
            "_thrs_interestingness": 0.41973,
            "_thrs_logistic_regression": 0.8996,
            "_thrs_random_forest": 0.96
        },
        {
            "expression": "\u22a2 ( \ud835\udf11 \u2192 A \u2208 V )",
            "prop_expression": " \u22a2 ( \ud835\udf11 \u2192 A \u2208 V )",
            "step": 40,
            "theorem": "caofref.1",
            "ground_truth": "caofref.1 \u22a2 ( \ud835\udf11 \u2192 A \u2208 V )",
            "ground_truth_display": false,
            "statement_depth": 0,
            "_thrs_random_uniform": 0.29469,
            "_thrs_reconstruct": 0.0,
            "_thrs_obviousness": 0.0,
            "_thrs_weight": 1.0,
            "_thrs_complexity": 0.75,
            "_thrs_surprisingness": 0.14202,
            "_thrs_intensity": 0.20661,
            "_thrs_interestingness": 0.41973,
            "_thrs_logistic_regression": 0.8996,
            "_thrs_random_forest": 0.96
        },
        {
            "expression": "\u22a2 ( A \u2229 A ) = A",
            "prop_expression": " \u22a2 ( A \u2229 A ) = A",
            "step": 41,
            "theorem": "inidm",
            "ground_truth": "inidm \u22a2 ( A \u2229 A ) = A",
            "ground_truth_display": false,
            "statement_depth": 0,
            "_thrs_random_uniform": 0.13835,
            "_thrs_reconstruct": 0.0,
            "_thrs_obviousness": 0.0,
            "_thrs_weight": 1.0,
            "_thrs_complexity": 1.0,
            "_thrs_surprisingness": 0.0,
            "_thrs_intensity": 0.04132,
            "_thrs_interestingness": 0.40826,
            "_thrs_logistic_regression": 0.55551,
            "_thrs_random_forest": 0.915
        },
        {
            "expression": "\u22a2 ( ( \ud835\udf11 \u2227 w \u2208 A ) \u2192 ( F ` w ) = ( F ` w ) )",
            "prop_expression": " \u22a2 ( \ud835\udf11 \u2192 A = A )",
            "step": 42,
            "theorem": "eqidd",
            "ground_truth": "eqidd \u22a2 ( ( \ud835\udf11 \u2227 w \u2208 A ) \u2192 ( F ` w ) = ( F ` w ) )",
            "ground_truth_display": false,
            "statement_depth": 0,
            "_thrs_random_uniform": 0.51749,
            "_thrs_reconstruct": 0.0,
            "_thrs_obviousness": 0.0,
            "_thrs_weight": 0.8125,
            "_thrs_complexity": 0.5,
            "_thrs_surprisingness": 0.29105,
            "_thrs_intensity": 0.07438,
            "_thrs_interestingness": 0.33559,
            "_thrs_logistic_regression": 0.91443,
            "_thrs_random_forest": 0.965
        },
        {
            "expression": "\u22a2 ( ( \ud835\udf11 \u2227 w \u2208 A ) \u2192 ( G ` w ) = ( G ` w ) )",
            "prop_expression": " \u22a2 ( \ud835\udf11 \u2192 A = A )",
            "step": 43,
            "theorem": "eqidd",
            "ground_truth": "eqidd \u22a2 ( ( \ud835\udf11 \u2227 w \u2208 A ) \u2192 ( G ` w ) = ( G ` w ) )",
            "ground_truth_display": false,
            "statement_depth": 0,
            "_thrs_random_uniform": 0.80611,
            "_thrs_reconstruct": 0.0,
            "_thrs_obviousness": 0.0,
            "_thrs_weight": 0.8125,
            "_thrs_complexity": 0.5,
            "_thrs_surprisingness": 0.29463,
            "_thrs_intensity": 0.07438,
            "_thrs_interestingness": 0.3363,
            "_thrs_logistic_regression": 0.91405,
            "_thrs_random_forest": 0.965
        }
    ]
}