{
    "theorem": "f1oiso2",
    "hyps": [
        [
            1,
            2
        ],
        [
            1,
            70
        ],
        [
            2,
            3
        ],
        [
            2,
            4
        ],
        [
            4,
            5
        ],
        [
            5,
            6
        ],
        [
            5,
            35
        ],
        [
            6,
            7
        ],
        [
            7,
            8
        ],
        [
            7,
            11
        ],
        [
            7,
            28
        ],
        [
            8,
            9
        ],
        [
            9,
            10
        ],
        [
            11,
            12
        ],
        [
            11,
            15
        ],
        [
            11,
            21
        ],
        [
            11,
            22
        ],
        [
            12,
            13
        ],
        [
            13,
            14
        ],
        [
            15,
            16
        ],
        [
            16,
            17
        ],
        [
            16,
            19
        ],
        [
            17,
            18
        ],
        [
            19,
            20
        ],
        [
            22,
            23
        ],
        [
            23,
            24
        ],
        [
            23,
            27
        ],
        [
            24,
            25
        ],
        [
            25,
            26
        ],
        [
            28,
            29
        ],
        [
            29,
            30
        ],
        [
            30,
            31
        ],
        [
            30,
            34
        ],
        [
            31,
            32
        ],
        [
            32,
            33
        ],
        [
            35,
            36
        ],
        [
            36,
            37
        ],
        [
            37,
            38
        ],
        [
            37,
            46
        ],
        [
            37,
            54
        ],
        [
            38,
            39
        ],
        [
            38,
            40
        ],
        [
            40,
            41
        ],
        [
            40,
            42
        ],
        [
            40,
            43
        ],
        [
            43,
            44
        ],
        [
            43,
            45
        ],
        [
            46,
            47
        ],
        [
            46,
            48
        ],
        [
            48,
            49
        ],
        [
            48,
            50
        ],
        [
            48,
            51
        ],
        [
            51,
            52
        ],
        [
            51,
            53
        ],
        [
            54,
            55
        ],
        [
            54,
            56
        ],
        [
            54,
            63
        ],
        [
            56,
            57
        ],
        [
            56,
            59
        ],
        [
            57,
            58
        ],
        [
            59,
            60
        ],
        [
            59,
            61
        ],
        [
            59,
            62
        ],
        [
            63,
            64
        ],
        [
            63,
            66
        ],
        [
            64,
            65
        ],
        [
            66,
            67
        ],
        [
            66,
            68
        ],
        [
            66,
            69
        ]
    ],
    "expression": "( H : A -1-1-onto\u2192 B \u2192 H Isom R , S ( A , B ) )",
    "steps": [
        {
            "expression": "\u22a2 ( H : A -1-1-onto\u2192 B \u2192 H Isom R , S ( A , B ) )",
            "prop_expression": "( \ud835\udf11 \u2192 \ud835\udf13 ), ( ( \ud835\udf11 \u2227 \ud835\udf13 ) \u2192 \ud835\udf12 ) \u22a2 ( \ud835\udf11 \u2192 \ud835\udf12 )",
            "step": 1,
            "theorem": "mpdan",
            "ground_truth": "mpdan \u22a2 ( H : A -1-1-onto\u2192 B \u2192 H Isom R , S ( A , B ) )",
            "ground_truth_display": false,
            "statement_depth": 0,
            "_thrs_random_uniform": 0.98656,
            "_thrs_reconstruct": 0.0,
            "_thrs_obviousness": 1.0,
            "_thrs_weight": 0.97561,
            "_thrs_complexity": 0.85714,
            "_thrs_surprisingness": 0.58339,
            "_thrs_intensity": 0.83381,
            "_thrs_interestingness": 0.84999,
            "_thrs_logistic_regression": 0.98695,
            "_thrs_random_forest": 0.885
        },
        {
            "expression": "\u22a2 ( H : A -1-1-onto\u2192 B \u2192 S = { \u27e8 x , y \u27e9 | \u2203 z \u2208 A \u2203 w \u2208 A ( ( x = ( H ` z ) \u2227 y = ( H ` w ) ) \u2227 z R w ) } )",
            "prop_expression": "A = B, ( \ud835\udf11 \u2192 B = C ) \u22a2 ( \ud835\udf11 \u2192 A = C )",
            "step": 2,
            "theorem": "syl5eq",
            "ground_truth": "syl5eq \u22a2 ( H : A -1-1-onto\u2192 B \u2192 S = { \u27e8 x , y \u27e9 | \u2203 z \u2208 A \u2203 w \u2208 A ( ( x = ( H ` z ) \u2227 y = ( H ` w ) ) \u2227 z R w ) } )",
            "ground_truth_display": false,
            "statement_depth": 0,
            "_thrs_random_uniform": 0.86655,
            "_thrs_reconstruct": 0.0,
            "_thrs_obviousness": 0.78511,
            "_thrs_weight": 0.60976,
            "_thrs_complexity": 0.0,
            "_thrs_surprisingness": 0.98952,
            "_thrs_intensity": 0.60445,
            "_thrs_interestingness": 0.59777,
            "_thrs_logistic_regression": 0.99859,
            "_thrs_random_forest": 0.97
        },
        {
            "expression": "\u22a2 S = { \u27e8 x , y \u27e9 | ( ( x \u2208 B \u2227 y \u2208 B ) \u2227 ( `' H ` x ) R ( `' H ` y ) ) }",
            "prop_expression": " \u22a2 S = { \u27e8 x , y \u27e9 | ( ( x \u2208 B \u2227 y \u2208 B ) \u2227 ( `' H ` x ) R ( `' H ` y ) ) }",
            "step": 3,
            "theorem": "f1oiso2.1",
            "ground_truth": "f1oiso2.1 \u22a2 S = { \u27e8 x , y \u27e9 | ( ( x \u2208 B \u2227 y \u2208 B ) \u2227 ( `' H ` x ) R ( `' H ` y ) ) }",
            "ground_truth_display": false,
            "statement_depth": 0,
            "_thrs_random_uniform": 0.25064,
            "_thrs_reconstruct": 0.0,
            "_thrs_obviousness": 0.0,
            "_thrs_weight": 0.7561,
            "_thrs_complexity": 0.42857,
            "_thrs_surprisingness": 1.0,
            "_thrs_intensity": 0.04821,
            "_thrs_interestingness": 0.44658,
            "_thrs_logistic_regression": 0.82872,
            "_thrs_random_forest": 0.74
        },
        {
            "expression": "\u22a2 ( H : A -1-1-onto\u2192 B \u2192 { \u27e8 x , y \u27e9 | ( ( x \u2208 B \u2227 y \u2208 B ) \u2227 ( `' H ` x ) R ( `' H ` y ) ) } = { \u27e8 x , y \u27e9 | \u2203 z \u2208 A \u2203 w \u2208 A ( ( x = ( H ` z ) \u2227 y = ( H ` w ) ) \u2227 z R w ) } )",
            "prop_expression": "( \ud835\udf11 \u2192 ( \ud835\udf13 \u2194 \ud835\udf12 ) ) \u22a2 ( \ud835\udf11 \u2192 { \u27e8 x , y \u27e9 | \ud835\udf13 } = { \u27e8 x , y \u27e9 | \ud835\udf12 } )",
            "step": 4,
            "theorem": "opabbidv",
            "ground_truth": "opabbidv \u22a2 ( H : A -1-1-onto\u2192 B \u2192 { \u27e8 x , y \u27e9 | ( ( x \u2208 B \u2227 y \u2208 B ) \u2227 ( `' H ` x ) R ( `' H ` y ) ) } = { \u27e8 x , y \u27e9 | \u2203 z \u2208 A \u2203 w \u2208 A ( ( x = ( H ` z ) \u2227 y = ( H ` w ) ) \u2227 z R w ) } )",
            "ground_truth_display": false,
            "statement_depth": 0,
            "_thrs_random_uniform": 0.14912,
            "_thrs_reconstruct": 0.0,
            "_thrs_obviousness": 0.78511,
            "_thrs_weight": 0.21951,
            "_thrs_complexity": 0.0,
            "_thrs_surprisingness": 0.83864,
            "_thrs_intensity": 0.17676,
            "_thrs_interestingness": 0.40401,
            "_thrs_logistic_regression": 0.9835,
            "_thrs_random_forest": 0.845
        },
        {
            "expression": "\u22a2 ( H : A -1-1-onto\u2192 B \u2192 ( ( ( x \u2208 B \u2227 y \u2208 B ) \u2227 ( `' H ` x ) R ( `' H ` y ) ) \u2194 \u2203 z \u2208 A \u2203 w \u2208 A ( ( x = ( H ` z ) \u2227 y = ( H ` w ) ) \u2227 z R w ) ) )",
            "prop_expression": "( \ud835\udf11 \u2192 ( \ud835\udf13 \u2192 \ud835\udf12 ) ), ( \ud835\udf11 \u2192 ( \ud835\udf12 \u2192 \ud835\udf13 ) ) \u22a2 ( \ud835\udf11 \u2192 ( \ud835\udf13 \u2194 \ud835\udf12 ) )",
            "step": 5,
            "theorem": "impbid",
            "ground_truth": "impbid \u22a2 ( H : A -1-1-onto\u2192 B \u2192 ( ( ( x \u2208 B \u2227 y \u2208 B ) \u2227 ( `' H ` x ) R ( `' H ` y ) ) \u2194 \u2203 z \u2208 A \u2203 w \u2208 A ( ( x = ( H ` z ) \u2227 y = ( H ` w ) ) \u2227 z R w ) ) )",
            "ground_truth_display": false,
            "statement_depth": 0,
            "_thrs_random_uniform": 0.98402,
            "_thrs_reconstruct": 0.0,
            "_thrs_obviousness": 0.78511,
            "_thrs_weight": 0.31707,
            "_thrs_complexity": 0.0,
            "_thrs_surprisingness": 0.83864,
            "_thrs_intensity": 0.53028,
            "_thrs_interestingness": 0.49422,
            "_thrs_logistic_regression": 0.99774,
            "_thrs_random_forest": 0.865
        },
        {
            "expression": "\u22a2 ( H : A -1-1-onto\u2192 B \u2192 ( ( ( x \u2208 B \u2227 y \u2208 B ) \u2227 ( `' H ` x ) R ( `' H ` y ) ) \u2192 \u2203 z \u2208 A \u2203 w \u2208 A ( ( x = ( H ` z ) \u2227 y = ( H ` w ) ) \u2227 z R w ) ) )",
            "prop_expression": "( ( \ud835\udf11 \u2227 \ud835\udf13 \u2227 \ud835\udf12 ) \u2192 \ud835\udf03 ) \u22a2 ( \ud835\udf11 \u2192 ( ( \ud835\udf13 \u2227 \ud835\udf12 ) \u2192 \ud835\udf03 ) )",
            "step": 6,
            "theorem": "3expib",
            "ground_truth": "3expib \u22a2 ( H : A -1-1-onto\u2192 B \u2192 ( ( ( x \u2208 B \u2227 y \u2208 B ) \u2227 ( `' H ` x ) R ( `' H ` y ) ) \u2192 \u2203 z \u2208 A \u2203 w \u2208 A ( ( x = ( H ` z ) \u2227 y = ( H ` w ) ) \u2227 z R w ) ) )",
            "ground_truth_display": false,
            "statement_depth": 0,
            "_thrs_random_uniform": 0.63009,
            "_thrs_reconstruct": 0.0,
            "_thrs_obviousness": 0.39273,
            "_thrs_weight": 0.31707,
            "_thrs_complexity": 0.0,
            "_thrs_surprisingness": 0.83864,
            "_thrs_intensity": 0.2089,
            "_thrs_interestingness": 0.35147,
            "_thrs_logistic_regression": 0.98772,
            "_thrs_random_forest": 0.79
        },
        {
            "expression": "\u22a2 ( ( H : A -1-1-onto\u2192 B \u2227 ( x \u2208 B \u2227 y \u2208 B ) \u2227 ( `' H ` x ) R ( `' H ` y ) ) \u2192 \u2203 z \u2208 A \u2203 w \u2208 A ( ( x = ( H ` z ) \u2227 y = ( H ` w ) ) \u2227 z R w ) )",
            "prop_expression": "( \ud835\udf11 \u2192 \ud835\udf13 ), ( \ud835\udf11 \u2192 \ud835\udf12 ), ( ( \ud835\udf13 \u2227 \ud835\udf12 ) \u2192 \ud835\udf03 ) \u22a2 ( \ud835\udf11 \u2192 \ud835\udf03 )",
            "step": 7,
            "theorem": "syl2anc",
            "ground_truth": "syl2anc \u22a2 ( ( H : A -1-1-onto\u2192 B \u2227 ( x \u2208 B \u2227 y \u2208 B ) \u2227 ( `' H ` x ) R ( `' H ` y ) ) \u2192 \u2203 z \u2208 A \u2203 w \u2208 A ( ( x = ( H ` z ) \u2227 y = ( H ` w ) ) \u2227 z R w ) )",
            "ground_truth_display": false,
            "statement_depth": 0,
            "_thrs_random_uniform": 0.18521,
            "_thrs_reconstruct": 0.0,
            "_thrs_obviousness": 0.39273,
            "_thrs_weight": 0.31707,
            "_thrs_complexity": 0.0,
            "_thrs_surprisingness": 0.83864,
            "_thrs_intensity": 0.84274,
            "_thrs_interestingness": 0.47824,
            "_thrs_logistic_regression": 0.99959,
            "_thrs_random_forest": 0.855
        },
        {
            "expression": "\u22a2 ( ( H : A -1-1-onto\u2192 B \u2227 ( x \u2208 B \u2227 y \u2208 B ) \u2227 ( `' H ` x ) R ( `' H ` y ) ) \u2192 ( `' H ` x ) \u2208 A )",
            "prop_expression": "( ( \ud835\udf11 \u2227 \ud835\udf13 ) \u2192 \ud835\udf12 ) \u22a2 ( ( \ud835\udf11 \u2227 \ud835\udf13 \u2227 \ud835\udf03 ) \u2192 \ud835\udf12 )",
            "step": 8,
            "theorem": "3adant3",
            "ground_truth": "3adant3 \u22a2 ( ( H : A -1-1-onto\u2192 B \u2227 ( x \u2208 B \u2227 y \u2208 B ) \u2227 ( `' H ` x ) R ( `' H ` y ) ) \u2192 ( `' H ` x ) \u2208 A )",
            "ground_truth_display": false,
            "statement_depth": 0,
            "_thrs_random_uniform": 0.29869,
            "_thrs_reconstruct": 0.0,
            "_thrs_obviousness": 0.05617,
            "_thrs_weight": 0.58537,
            "_thrs_complexity": 0.28571,
            "_thrs_surprisingness": 0.83864,
            "_thrs_intensity": 0.11606,
            "_thrs_interestingness": 0.37639,
            "_thrs_logistic_regression": 0.93817,
            "_thrs_random_forest": 0.74
        },
        {
            "expression": "\u22a2 ( ( H : A -1-1-onto\u2192 B \u2227 ( x \u2208 B \u2227 y \u2208 B ) ) \u2192 ( `' H ` x ) \u2208 A )",
            "prop_expression": "( ( \ud835\udf11 \u2227 \ud835\udf13 ) \u2192 \ud835\udf12 ) \u22a2 ( ( \ud835\udf11 \u2227 ( \ud835\udf13 \u2227 \ud835\udf03 ) ) \u2192 \ud835\udf12 )",
            "step": 9,
            "theorem": "adantrr",
            "ground_truth": "adantrr \u22a2 ( ( H : A -1-1-onto\u2192 B \u2227 ( x \u2208 B \u2227 y \u2208 B ) ) \u2192 ( `' H ` x ) \u2208 A )",
            "ground_truth_display": false,
            "statement_depth": 0,
            "_thrs_random_uniform": 0.66721,
            "_thrs_reconstruct": 0.0,
            "_thrs_obviousness": 0.05617,
            "_thrs_weight": 0.80488,
            "_thrs_complexity": 0.42857,
            "_thrs_surprisingness": 0.51252,
            "_thrs_intensity": 0.18128,
            "_thrs_interestingness": 0.39668,
            "_thrs_logistic_regression": 0.95242,
            "_thrs_random_forest": 0.575
        },
        {
            "expression": "\u22a2 ( ( H : A -1-1-onto\u2192 B \u2227 x \u2208 B ) \u2192 ( `' H ` x ) \u2208 A )",
            "prop_expression": " \u22a2 ( ( F : A -1-1-onto\u2192 B \u2227 C \u2208 B ) \u2192 ( `' F ` C ) \u2208 A )",
            "step": 10,
            "theorem": "f1ocnvdm",
            "ground_truth": "f1ocnvdm \u22a2 ( ( H : A -1-1-onto\u2192 B \u2227 x \u2208 B ) \u2192 ( `' H ` x ) \u2208 A )",
            "ground_truth_display": false,
            "statement_depth": 0,
            "_thrs_random_uniform": 0.59678,
            "_thrs_reconstruct": 0.2614,
            "_thrs_obviousness": 0.05617,
            "_thrs_weight": 0.87805,
            "_thrs_complexity": 0.57143,
            "_thrs_surprisingness": 0.51252,
            "_thrs_intensity": 0.08529,
            "_thrs_interestingness": 0.42069,
            "_thrs_logistic_regression": 0.86087,
            "_thrs_random_forest": 0.59
        },
        {
            "expression": "\u22a2 ( ( H : A -1-1-onto\u2192 B \u2227 ( x \u2208 B \u2227 y \u2208 B ) \u2227 ( `' H ` x ) R ( `' H ` y ) ) \u2192 \u2203 w \u2208 A ( ( x = ( H ` ( `' H ` x ) ) \u2227 y = ( H ` w ) ) \u2227 ( `' H ` x ) R w ) )",
            "prop_expression": "( \ud835\udf11 \u2192 \ud835\udf13 ), ( \ud835\udf11 \u2192 \ud835\udf12 ), ( \ud835\udf11 \u2192 \ud835\udf03 ), ( ( \ud835\udf13 \u2227 ( \ud835\udf12 \u2227 \ud835\udf03 ) ) \u2192 \ud835\udf0f ) \u22a2 ( \ud835\udf11 \u2192 \ud835\udf0f )",
            "step": 11,
            "theorem": "syl12anc",
            "ground_truth": "syl12anc \u22a2 ( ( H : A -1-1-onto\u2192 B \u2227 ( x \u2208 B \u2227 y \u2208 B ) \u2227 ( `' H ` x ) R ( `' H ` y ) ) \u2192 \u2203 w \u2208 A ( ( x = ( H ` ( `' H ` x ) ) \u2227 y = ( H ` w ) ) \u2227 ( `' H ` x ) R w ) )",
            "ground_truth_display": false,
            "statement_depth": 0,
            "_thrs_random_uniform": 0.03014,
            "_thrs_reconstruct": 0.0,
            "_thrs_obviousness": 0.33634,
            "_thrs_weight": 0.2439,
            "_thrs_complexity": 0.14286,
            "_thrs_surprisingness": 0.83864,
            "_thrs_intensity": 1.0,
            "_thrs_interestingness": 0.51235,
            "_thrs_logistic_regression": 0.99962,
            "_thrs_random_forest": 0.845
        },
        {
            "expression": "\u22a2 ( ( H : A -1-1-onto\u2192 B \u2227 ( x \u2208 B \u2227 y \u2208 B ) \u2227 ( `' H ` x ) R ( `' H ` y ) ) \u2192 ( `' H ` y ) \u2208 A )",
            "prop_expression": "( ( \ud835\udf11 \u2227 \ud835\udf13 ) \u2192 \ud835\udf12 ) \u22a2 ( ( \ud835\udf11 \u2227 \ud835\udf13 \u2227 \ud835\udf03 ) \u2192 \ud835\udf12 )",
            "step": 12,
            "theorem": "3adant3",
            "ground_truth": "3adant3 \u22a2 ( ( H : A -1-1-onto\u2192 B \u2227 ( x \u2208 B \u2227 y \u2208 B ) \u2227 ( `' H ` x ) R ( `' H ` y ) ) \u2192 ( `' H ` y ) \u2208 A )",
            "ground_truth_display": false,
            "statement_depth": 0,
            "_thrs_random_uniform": 0.06063,
            "_thrs_reconstruct": 0.0,
            "_thrs_obviousness": 0.05617,
            "_thrs_weight": 0.58537,
            "_thrs_complexity": 0.28571,
            "_thrs_surprisingness": 0.83864,
            "_thrs_intensity": 0.11606,
            "_thrs_interestingness": 0.37639,
            "_thrs_logistic_regression": 0.93817,
            "_thrs_random_forest": 0.715
        },
        {
            "expression": "\u22a2 ( ( H : A -1-1-onto\u2192 B \u2227 ( x \u2208 B \u2227 y \u2208 B ) ) \u2192 ( `' H ` y ) \u2208 A )",
            "prop_expression": "( ( \ud835\udf11 \u2227 \ud835\udf13 ) \u2192 \ud835\udf12 ) \u22a2 ( ( \ud835\udf11 \u2227 ( \ud835\udf03 \u2227 \ud835\udf13 ) ) \u2192 \ud835\udf12 )",
            "step": 13,
            "theorem": "adantrl",
            "ground_truth": "adantrl \u22a2 ( ( H : A -1-1-onto\u2192 B \u2227 ( x \u2208 B \u2227 y \u2208 B ) ) \u2192 ( `' H ` y ) \u2208 A )",
            "ground_truth_display": false,
            "statement_depth": 0,
            "_thrs_random_uniform": 0.17531,
            "_thrs_reconstruct": 0.0,
            "_thrs_obviousness": 0.05617,
            "_thrs_weight": 0.80488,
            "_thrs_complexity": 0.42857,
            "_thrs_surprisingness": 0.51252,
            "_thrs_intensity": 0.18128,
            "_thrs_interestingness": 0.39668,
            "_thrs_logistic_regression": 0.95242,
            "_thrs_random_forest": 0.575
        },
        {
            "expression": "\u22a2 ( ( H : A -1-1-onto\u2192 B \u2227 y \u2208 B ) \u2192 ( `' H ` y ) \u2208 A )",
            "prop_expression": " \u22a2 ( ( F : A -1-1-onto\u2192 B \u2227 C \u2208 B ) \u2192 ( `' F ` C ) \u2208 A )",
            "step": 14,
            "theorem": "f1ocnvdm",
            "ground_truth": "f1ocnvdm \u22a2 ( ( H : A -1-1-onto\u2192 B \u2227 y \u2208 B ) \u2192 ( `' H ` y ) \u2208 A )",
            "ground_truth_display": false,
            "statement_depth": 0,
            "_thrs_random_uniform": 0.27571,
            "_thrs_reconstruct": 0.2614,
            "_thrs_obviousness": 0.05617,
            "_thrs_weight": 0.87805,
            "_thrs_complexity": 0.57143,
            "_thrs_surprisingness": 0.51252,
            "_thrs_intensity": 0.08529,
            "_thrs_interestingness": 0.42069,
            "_thrs_logistic_regression": 0.86087,
            "_thrs_random_forest": 0.59
        },
        {
            "expression": "\u22a2 ( ( H : A -1-1-onto\u2192 B \u2227 ( x \u2208 B \u2227 y \u2208 B ) \u2227 ( `' H ` x ) R ( `' H ` y ) ) \u2192 ( x = ( H ` ( `' H ` x ) ) \u2227 y = ( H ` ( `' H ` y ) ) ) )",
            "prop_expression": "( ( \ud835\udf11 \u2227 \ud835\udf13 ) \u2192 \ud835\udf12 ) \u22a2 ( ( \ud835\udf11 \u2227 \ud835\udf13 \u2227 \ud835\udf03 ) \u2192 \ud835\udf12 )",
            "step": 15,
            "theorem": "3adant3",
            "ground_truth": "3adant3 \u22a2 ( ( H : A -1-1-onto\u2192 B \u2227 ( x \u2208 B \u2227 y \u2208 B ) \u2227 ( `' H ` x ) R ( `' H ` y ) ) \u2192 ( x = ( H ` ( `' H ` x ) ) \u2227 y = ( H ` ( `' H ` y ) ) ) )",
            "ground_truth_display": false,
            "statement_depth": 0,
            "_thrs_random_uniform": 0.42636,
            "_thrs_reconstruct": 0.0,
            "_thrs_obviousness": 0.27994,
            "_thrs_weight": 0.39024,
            "_thrs_complexity": 0.28571,
            "_thrs_surprisingness": 0.83864,
            "_thrs_intensity": 0.14722,
            "_thrs_interestingness": 0.38835,
            "_thrs_logistic_regression": 0.93598,
            "_thrs_random_forest": 0.68
        },
        {
            "expression": "\u22a2 ( ( H : A -1-1-onto\u2192 B \u2227 ( x \u2208 B \u2227 y \u2208 B ) ) \u2192 ( x = ( H ` ( `' H ` x ) ) \u2227 y = ( H ` ( `' H ` y ) ) ) )",
            "prop_expression": "( ( \ud835\udf11 \u2227 \ud835\udf13 ) \u2192 \ud835\udf12 ), ( ( \ud835\udf11 \u2227 \ud835\udf03 ) \u2192 \ud835\udf0f ) \u22a2 ( ( \ud835\udf11 \u2227 ( \ud835\udf13 \u2227 \ud835\udf03 ) ) \u2192 ( \ud835\udf12 \u2227 \ud835\udf0f ) )",
            "step": 16,
            "theorem": "anim12dan",
            "ground_truth": "anim12dan \u22a2 ( ( H : A -1-1-onto\u2192 B \u2227 ( x \u2208 B \u2227 y \u2208 B ) ) \u2192 ( x = ( H ` ( `' H ` x ) ) \u2227 y = ( H ` ( `' H ` y ) ) ) )",
            "ground_truth_display": false,
            "statement_depth": 0,
            "_thrs_random_uniform": 0.90107,
            "_thrs_reconstruct": 0.0,
            "_thrs_obviousness": 0.27994,
            "_thrs_weight": 0.60976,
            "_thrs_complexity": 0.42857,
            "_thrs_surprisingness": 0.51252,
            "_thrs_intensity": 0.26246,
            "_thrs_interestingness": 0.41865,
            "_thrs_logistic_regression": 0.96193,
            "_thrs_random_forest": 0.815
        },
        {
            "expression": "\u22a2 ( ( H : A -1-1-onto\u2192 B \u2227 x \u2208 B ) \u2192 x = ( H ` ( `' H ` x ) ) )",
            "prop_expression": "( \ud835\udf11 \u2192 A = B ) \u22a2 ( \ud835\udf11 \u2192 B = A )",
            "step": 17,
            "theorem": "eqcomd",
            "ground_truth": "eqcomd \u22a2 ( ( H : A -1-1-onto\u2192 B \u2227 x \u2208 B ) \u2192 x = ( H ` ( `' H ` x ) ) )",
            "ground_truth_display": false,
            "statement_depth": 0,
            "_thrs_random_uniform": 0.17448,
            "_thrs_reconstruct": 0.0,
            "_thrs_obviousness": 0.13997,
            "_thrs_weight": 0.85366,
            "_thrs_complexity": 0.57143,
            "_thrs_surprisingness": 0.51252,
            "_thrs_intensity": 0.2089,
            "_thrs_interestingness": 0.4573,
            "_thrs_logistic_regression": 0.92122,
            "_thrs_random_forest": 0.775
        },
        {
            "expression": "\u22a2 ( ( H : A -1-1-onto\u2192 B \u2227 x \u2208 B ) \u2192 ( H ` ( `' H ` x ) ) = x )",
            "prop_expression": " \u22a2 ( ( F : A -1-1-onto\u2192 B \u2227 C \u2208 B ) \u2192 ( F ` ( `' F ` C ) ) = C )",
            "step": 18,
            "theorem": "f1ocnvfv2",
            "ground_truth": "f1ocnvfv2 \u22a2 ( ( H : A -1-1-onto\u2192 B \u2227 x \u2208 B ) \u2192 ( H ` ( `' H ` x ) ) = x )",
            "ground_truth_display": false,
            "statement_depth": 0,
            "_thrs_random_uniform": 0.9202,
            "_thrs_reconstruct": 0.65138,
            "_thrs_obviousness": 0.13997,
            "_thrs_weight": 0.85366,
            "_thrs_complexity": 0.57143,
            "_thrs_surprisingness": 0.51252,
            "_thrs_intensity": 0.07116,
            "_thrs_interestingness": 0.42975,
            "_thrs_logistic_regression": 0.8476,
            "_thrs_random_forest": 0.75
        },
        {
            "expression": "\u22a2 ( ( H : A -1-1-onto\u2192 B \u2227 y \u2208 B ) \u2192 y = ( H ` ( `' H ` y ) ) )",
            "prop_expression": "( \ud835\udf11 \u2192 A = B ) \u22a2 ( \ud835\udf11 \u2192 B = A )",
            "step": 19,
            "theorem": "eqcomd",
            "ground_truth": "eqcomd \u22a2 ( ( H : A -1-1-onto\u2192 B \u2227 y \u2208 B ) \u2192 y = ( H ` ( `' H ` y ) ) )",
            "ground_truth_display": false,
            "statement_depth": 0,
            "_thrs_random_uniform": 0.96663,
            "_thrs_reconstruct": 0.0,
            "_thrs_obviousness": 0.13997,
            "_thrs_weight": 0.85366,
            "_thrs_complexity": 0.57143,
            "_thrs_surprisingness": 0.51252,
            "_thrs_intensity": 0.2089,
            "_thrs_interestingness": 0.4573,
            "_thrs_logistic_regression": 0.92122,
            "_thrs_random_forest": 0.775
        },
        {
            "expression": "\u22a2 ( ( H : A -1-1-onto\u2192 B \u2227 y \u2208 B ) \u2192 ( H ` ( `' H ` y ) ) = y )",
            "prop_expression": " \u22a2 ( ( F : A -1-1-onto\u2192 B \u2227 C \u2208 B ) \u2192 ( F ` ( `' F ` C ) ) = C )",
            "step": 20,
            "theorem": "f1ocnvfv2",
            "ground_truth": "f1ocnvfv2 \u22a2 ( ( H : A -1-1-onto\u2192 B \u2227 y \u2208 B ) \u2192 ( H ` ( `' H ` y ) ) = y )",
            "ground_truth_display": false,
            "statement_depth": 0,
            "_thrs_random_uniform": 0.48618,
            "_thrs_reconstruct": 0.65138,
            "_thrs_obviousness": 0.13997,
            "_thrs_weight": 0.85366,
            "_thrs_complexity": 0.57143,
            "_thrs_surprisingness": 0.51252,
            "_thrs_intensity": 0.07116,
            "_thrs_interestingness": 0.42975,
            "_thrs_logistic_regression": 0.8476,
            "_thrs_random_forest": 0.75
        },
        {
            "expression": "\u22a2 ( ( H : A -1-1-onto\u2192 B \u2227 ( x \u2208 B \u2227 y \u2208 B ) \u2227 ( `' H ` x ) R ( `' H ` y ) ) \u2192 ( `' H ` x ) R ( `' H ` y ) )",
            "prop_expression": " \u22a2 ( ( \ud835\udf11 \u2227 \ud835\udf13 \u2227 \ud835\udf12 ) \u2192 \ud835\udf12 )",
            "step": 21,
            "theorem": "simp3",
            "ground_truth": "simp3 \u22a2 ( ( H : A -1-1-onto\u2192 B \u2227 ( x \u2208 B \u2227 y \u2208 B ) \u2227 ( `' H ` x ) R ( `' H ` y ) ) \u2192 ( `' H ` x ) R ( `' H ` y ) )",
            "ground_truth_display": false,
            "statement_depth": 0,
            "_thrs_random_uniform": 0.23756,
            "_thrs_reconstruct": 0.0,
            "_thrs_obviousness": 0.0,
            "_thrs_weight": 0.5122,
            "_thrs_complexity": 0.28571,
            "_thrs_surprisingness": 0.83864,
            "_thrs_intensity": 0.0023,
            "_thrs_interestingness": 0.32777,
            "_thrs_logistic_regression": 0.885,
            "_thrs_random_forest": 0.68
        },
        {
            "expression": "\u22a2 ( ( ( `' H ` y ) \u2208 A \u2227 ( ( x = ( H ` ( `' H ` x ) ) \u2227 y = ( H ` ( `' H ` y ) ) ) \u2227 ( `' H ` x ) R ( `' H ` y ) ) ) \u2192 \u2203 w \u2208 A ( ( x = ( H ` ( `' H ` x ) ) \u2227 y = ( H ` w ) ) \u2227 ( `' H ` x ) R w ) )",
            "prop_expression": "( x = A \u2192 ( \ud835\udf11 \u2194 \ud835\udf13 ) ) \u22a2 ( ( A \u2208 B \u2227 \ud835\udf13 ) \u2192 \u2203 x \u2208 B \ud835\udf11 )",
            "step": 22,
            "theorem": "rcla4ev",
            "ground_truth": "rcla4ev \u22a2 ( ( ( `' H ` y ) \u2208 A \u2227 ( ( x = ( H ` ( `' H ` x ) ) \u2227 y = ( H ` ( `' H ` y ) ) ) \u2227 ( `' H ` x ) R ( `' H ` y ) ) ) \u2192 \u2203 w \u2208 A ( ( x = ( H ` ( `' H ` x ) ) \u2227 y = ( H ` w ) ) \u2227 ( `' H ` x ) R w ) )",
            "ground_truth_display": false,
            "statement_depth": 0,
            "_thrs_random_uniform": 0.7877,
            "_thrs_reconstruct": 0.0,
            "_thrs_obviousness": 0.00022,
            "_thrs_weight": 0.0,
            "_thrs_complexity": 0.42857,
            "_thrs_surprisingness": 0.47295,
            "_thrs_intensity": 0.26699,
            "_thrs_interestingness": 0.23375,
            "_thrs_logistic_regression": 0.9399,
            "_thrs_random_forest": 0.61
        },
        {
            "expression": "\u22a2 ( w = ( `' H ` y ) \u2192 ( ( ( x = ( H ` ( `' H ` x ) ) \u2227 y = ( H ` w ) ) \u2227 ( `' H ` x ) R w ) \u2194 ( ( x = ( H ` ( `' H ` x ) ) \u2227 y = ( H ` ( `' H ` y ) ) ) \u2227 ( `' H ` x ) R ( `' H ` y ) ) ) )",
            "prop_expression": "( \ud835\udf11 \u2192 ( \ud835\udf13 \u2194 \ud835\udf12 ) ), ( \ud835\udf11 \u2192 ( \ud835\udf03 \u2194 \ud835\udf0f ) ) \u22a2 ( \ud835\udf11 \u2192 ( ( \ud835\udf13 \u2227 \ud835\udf03 ) \u2194 ( \ud835\udf12 \u2227 \ud835\udf0f ) ) )",
            "step": 23,
            "theorem": "anbi12d",
            "ground_truth": "anbi12d \u22a2 ( w = ( `' H ` y ) \u2192 ( ( ( x = ( H ` ( `' H ` x ) ) \u2227 y = ( H ` w ) ) \u2227 ( `' H ` x ) R w ) \u2194 ( ( x = ( H ` ( `' H ` x ) ) \u2227 y = ( H ` ( `' H ` y ) ) ) \u2227 ( `' H ` x ) R ( `' H ` y ) ) ) )",
            "ground_truth_display": false,
            "statement_depth": 0,
            "_thrs_random_uniform": 0.22713,
            "_thrs_reconstruct": 0.0,
            "_thrs_obviousness": 0.00022,
            "_thrs_weight": 0.09756,
            "_thrs_complexity": 0.71429,
            "_thrs_surprisingness": 0.15826,
            "_thrs_intensity": 0.24461,
            "_thrs_interestingness": 0.24299,
            "_thrs_logistic_regression": 0.84508,
            "_thrs_random_forest": 0.475
        },
        {
            "expression": "\u22a2 ( w = ( `' H ` y ) \u2192 ( ( x = ( H ` ( `' H ` x ) ) \u2227 y = ( H ` w ) ) \u2194 ( x = ( H ` ( `' H ` x ) ) \u2227 y = ( H ` ( `' H ` y ) ) ) ) )",
            "prop_expression": "( \ud835\udf11 \u2192 ( \ud835\udf13 \u2194 \ud835\udf12 ) ) \u22a2 ( \ud835\udf11 \u2192 ( ( \ud835\udf03 \u2227 \ud835\udf13 ) \u2194 ( \ud835\udf03 \u2227 \ud835\udf12 ) ) )",
            "step": 24,
            "theorem": "anbi2d",
            "ground_truth": "anbi2d \u22a2 ( w = ( `' H ` y ) \u2192 ( ( x = ( H ` ( `' H ` x ) ) \u2227 y = ( H ` w ) ) \u2194 ( x = ( H ` ( `' H ` x ) ) \u2227 y = ( H ` ( `' H ` y ) ) ) ) )",
            "ground_truth_display": false,
            "statement_depth": 0,
            "_thrs_random_uniform": 0.85971,
            "_thrs_reconstruct": 0.0,
            "_thrs_obviousness": 0.00018,
            "_thrs_weight": 0.46341,
            "_thrs_complexity": 0.85714,
            "_thrs_surprisingness": 0.0,
            "_thrs_intensity": 0.0932,
            "_thrs_interestingness": 0.28279,
            "_thrs_logistic_regression": 0.67195,
            "_thrs_random_forest": 0.3
        },
        {
            "expression": "\u22a2 ( w = ( `' H ` y ) \u2192 ( y = ( H ` w ) \u2194 y = ( H ` ( `' H ` y ) ) ) )",
            "prop_expression": "( \ud835\udf11 \u2192 A = B ) \u22a2 ( \ud835\udf11 \u2192 ( C = A \u2194 C = B ) )",
            "step": 25,
            "theorem": "eqeq2d",
            "ground_truth": "eqeq2d \u22a2 ( w = ( `' H ` y ) \u2192 ( y = ( H ` w ) \u2194 y = ( H ` ( `' H ` y ) ) ) )",
            "ground_truth_display": false,
            "statement_depth": 0,
            "_thrs_random_uniform": 0.11537,
            "_thrs_reconstruct": 0.0,
            "_thrs_obviousness": 0.00018,
            "_thrs_weight": 0.80488,
            "_thrs_complexity": 1.0,
            "_thrs_surprisingness": 0.0,
            "_thrs_intensity": 0.16873,
            "_thrs_interestingness": 0.39476,
            "_thrs_logistic_regression": 0.67355,
            "_thrs_random_forest": 0.485
        },
        {
            "expression": "\u22a2 ( w = ( `' H ` y ) \u2192 ( H ` w ) = ( H ` ( `' H ` y ) ) )",
            "prop_expression": " \u22a2 ( A = B \u2192 ( F ` A ) = ( F ` B ) )",
            "step": 26,
            "theorem": "fveq2",
            "ground_truth": "fveq2 \u22a2 ( w = ( `' H ` y ) \u2192 ( H ` w ) = ( H ` ( `' H ` y ) ) )",
            "ground_truth_display": false,
            "statement_depth": 0,
            "_thrs_random_uniform": 0.60869,
            "_thrs_reconstruct": 0.00083,
            "_thrs_obviousness": 0.00018,
            "_thrs_weight": 0.85366,
            "_thrs_complexity": 1.0,
            "_thrs_surprisingness": 0.0,
            "_thrs_intensity": 0.0023,
            "_thrs_interestingness": 0.37123,
            "_thrs_logistic_regression": 0.46824,
            "_thrs_random_forest": 0.53
        },
        {
            "expression": "\u22a2 ( w = ( `' H ` y ) \u2192 ( ( `' H ` x ) R w \u2194 ( `' H ` x ) R ( `' H ` y ) ) )",
            "prop_expression": " \u22a2 ( A = B \u2192 ( C R A \u2194 C R B ) )",
            "step": 27,
            "theorem": "breq2",
            "ground_truth": "breq2 \u22a2 ( w = ( `' H ` y ) \u2192 ( ( `' H ` x ) R w \u2194 ( `' H ` x ) R ( `' H ` y ) ) )",
            "ground_truth_display": false,
            "statement_depth": 0,
            "_thrs_random_uniform": 0.27129,
            "_thrs_reconstruct": 0.00021,
            "_thrs_obviousness": 4e-05,
            "_thrs_weight": 0.70732,
            "_thrs_complexity": 0.71429,
            "_thrs_surprisingness": 0.15826,
            "_thrs_intensity": 0.0,
            "_thrs_interestingness": 0.31598,
            "_thrs_logistic_regression": 0.72278,
            "_thrs_random_forest": 0.36
        },
        {
            "expression": "\u22a2 ( ( ( `' H ` x ) \u2208 A \u2227 \u2203 w \u2208 A ( ( x = ( H ` ( `' H ` x ) ) \u2227 y = ( H ` w ) ) \u2227 ( `' H ` x ) R w ) ) \u2192 \u2203 z \u2208 A \u2203 w \u2208 A ( ( x = ( H ` z ) \u2227 y = ( H ` w ) ) \u2227 z R w ) )",
            "prop_expression": "( x = A \u2192 ( \ud835\udf11 \u2194 \ud835\udf13 ) ) \u22a2 ( ( A \u2208 B \u2227 \ud835\udf13 ) \u2192 \u2203 x \u2208 B \ud835\udf11 )",
            "step": 28,
            "theorem": "rcla4ev",
            "ground_truth": "rcla4ev \u22a2 ( ( ( `' H ` x ) \u2208 A \u2227 \u2203 w \u2208 A ( ( x = ( H ` ( `' H ` x ) ) \u2227 y = ( H ` w ) ) \u2227 ( `' H ` x ) R w ) ) \u2192 \u2203 z \u2208 A \u2203 w \u2208 A ( ( x = ( H ` z ) \u2227 y = ( H ` w ) ) \u2227 z R w ) )",
            "ground_truth_display": false,
            "statement_depth": 0,
            "_thrs_random_uniform": 0.39022,
            "_thrs_reconstruct": 0.0,
            "_thrs_obviousness": 0.00022,
            "_thrs_weight": 0.14634,
            "_thrs_complexity": 0.28571,
            "_thrs_surprisingness": 0.47295,
            "_thrs_intensity": 0.179,
            "_thrs_interestingness": 0.21685,
            "_thrs_logistic_regression": 0.95853,
            "_thrs_random_forest": 0.77
        },
        {
            "expression": "\u22a2 ( z = ( `' H ` x ) \u2192 ( \u2203 w \u2208 A ( ( x = ( H ` z ) \u2227 y = ( H ` w ) ) \u2227 z R w ) \u2194 \u2203 w \u2208 A ( ( x = ( H ` ( `' H ` x ) ) \u2227 y = ( H ` w ) ) \u2227 ( `' H ` x ) R w ) ) )",
            "prop_expression": "( \ud835\udf11 \u2192 ( \ud835\udf13 \u2194 \ud835\udf12 ) ) \u22a2 ( \ud835\udf11 \u2192 ( \u2203 x \u2208 A \ud835\udf13 \u2194 \u2203 x \u2208 A \ud835\udf12 ) )",
            "step": 29,
            "theorem": "rexbidv",
            "ground_truth": "rexbidv \u22a2 ( z = ( `' H ` x ) \u2192 ( \u2203 w \u2208 A ( ( x = ( H ` z ) \u2227 y = ( H ` w ) ) \u2227 z R w ) \u2194 \u2203 w \u2208 A ( ( x = ( H ` ( `' H ` x ) ) \u2227 y = ( H ` w ) ) \u2227 ( `' H ` x ) R w ) ) )",
            "ground_truth_display": false,
            "statement_depth": 0,
            "_thrs_random_uniform": 0.5511,
            "_thrs_reconstruct": 0.0,
            "_thrs_obviousness": 0.00022,
            "_thrs_weight": 0.2439,
            "_thrs_complexity": 0.28571,
            "_thrs_surprisingness": 0.47295,
            "_thrs_intensity": 0.22744,
            "_thrs_interestingness": 0.24605,
            "_thrs_logistic_regression": 0.97054,
            "_thrs_random_forest": 0.52
        },
        {
            "expression": "\u22a2 ( z = ( `' H ` x ) \u2192 ( ( ( x = ( H ` z ) \u2227 y = ( H ` w ) ) \u2227 z R w ) \u2194 ( ( x = ( H ` ( `' H ` x ) ) \u2227 y = ( H ` w ) ) \u2227 ( `' H ` x ) R w ) ) )",
            "prop_expression": "( \ud835\udf11 \u2192 ( \ud835\udf13 \u2194 \ud835\udf12 ) ), ( \ud835\udf11 \u2192 ( \ud835\udf03 \u2194 \ud835\udf0f ) ) \u22a2 ( \ud835\udf11 \u2192 ( ( \ud835\udf13 \u2227 \ud835\udf03 ) \u2194 ( \ud835\udf12 \u2227 \ud835\udf0f ) ) )",
            "step": 30,
            "theorem": "anbi12d",
            "ground_truth": "anbi12d \u22a2 ( z = ( `' H ` x ) \u2192 ( ( ( x = ( H ` z ) \u2227 y = ( H ` w ) ) \u2227 z R w ) \u2194 ( ( x = ( H ` ( `' H ` x ) ) \u2227 y = ( H ` w ) ) \u2227 ( `' H ` x ) R w ) ) )",
            "ground_truth_display": false,
            "statement_depth": 0,
            "_thrs_random_uniform": 0.70309,
            "_thrs_reconstruct": 0.0,
            "_thrs_obviousness": 0.00022,
            "_thrs_weight": 0.39024,
            "_thrs_complexity": 0.57143,
            "_thrs_surprisingness": 0.15826,
            "_thrs_intensity": 0.25759,
            "_thrs_interestingness": 0.27555,
            "_thrs_logistic_regression": 0.94112,
            "_thrs_random_forest": 0.715
        },
        {
            "expression": "\u22a2 ( z = ( `' H ` x ) \u2192 ( ( x = ( H ` z ) \u2227 y = ( H ` w ) ) \u2194 ( x = ( H ` ( `' H ` x ) ) \u2227 y = ( H ` w ) ) ) )",
            "prop_expression": "( \ud835\udf11 \u2192 ( \ud835\udf13 \u2194 \ud835\udf12 ) ) \u22a2 ( \ud835\udf11 \u2192 ( ( \ud835\udf13 \u2227 \ud835\udf03 ) \u2194 ( \ud835\udf12 \u2227 \ud835\udf03 ) ) )",
            "step": 31,
            "theorem": "anbi1d",
            "ground_truth": "anbi1d \u22a2 ( z = ( `' H ` x ) \u2192 ( ( x = ( H ` z ) \u2227 y = ( H ` w ) ) \u2194 ( x = ( H ` ( `' H ` x ) ) \u2227 y = ( H ` w ) ) ) )",
            "ground_truth_display": false,
            "statement_depth": 0,
            "_thrs_random_uniform": 0.12177,
            "_thrs_reconstruct": 0.0,
            "_thrs_obviousness": 0.00018,
            "_thrs_weight": 0.60976,
            "_thrs_complexity": 0.71429,
            "_thrs_surprisingness": 0.0,
            "_thrs_intensity": 0.18747,
            "_thrs_interestingness": 0.30234,
            "_thrs_logistic_regression": 0.89004,
            "_thrs_random_forest": 0.56
        },
        {
            "expression": "\u22a2 ( z = ( `' H ` x ) \u2192 ( x = ( H ` z ) \u2194 x = ( H ` ( `' H ` x ) ) ) )",
            "prop_expression": "( \ud835\udf11 \u2192 A = B ) \u22a2 ( \ud835\udf11 \u2192 ( C = A \u2194 C = B ) )",
            "step": 32,
            "theorem": "eqeq2d",
            "ground_truth": "eqeq2d \u22a2 ( z = ( `' H ` x ) \u2192 ( x = ( H ` z ) \u2194 x = ( H ` ( `' H ` x ) ) ) )",
            "ground_truth_display": false,
            "statement_depth": 0,
            "_thrs_random_uniform": 0.62775,
            "_thrs_reconstruct": 0.0,
            "_thrs_obviousness": 0.00018,
            "_thrs_weight": 0.80488,
            "_thrs_complexity": 1.0,
            "_thrs_surprisingness": 0.0,
            "_thrs_intensity": 0.16873,
            "_thrs_interestingness": 0.39476,
            "_thrs_logistic_regression": 0.67355,
            "_thrs_random_forest": 0.65
        },
        {
            "expression": "\u22a2 ( z = ( `' H ` x ) \u2192 ( H ` z ) = ( H ` ( `' H ` x ) ) )",
            "prop_expression": " \u22a2 ( A = B \u2192 ( F ` A ) = ( F ` B ) )",
            "step": 33,
            "theorem": "fveq2",
            "ground_truth": "fveq2 \u22a2 ( z = ( `' H ` x ) \u2192 ( H ` z ) = ( H ` ( `' H ` x ) ) )",
            "ground_truth_display": false,
            "statement_depth": 0,
            "_thrs_random_uniform": 0.67755,
            "_thrs_reconstruct": 0.00083,
            "_thrs_obviousness": 0.00018,
            "_thrs_weight": 0.85366,
            "_thrs_complexity": 1.0,
            "_thrs_surprisingness": 0.0,
            "_thrs_intensity": 0.0023,
            "_thrs_interestingness": 0.37123,
            "_thrs_logistic_regression": 0.46824,
            "_thrs_random_forest": 0.53
        },
        {
            "expression": "\u22a2 ( z = ( `' H ` x ) \u2192 ( z R w \u2194 ( `' H ` x ) R w ) )",
            "prop_expression": " \u22a2 ( A = B \u2192 ( A R C \u2194 B R C ) )",
            "step": 34,
            "theorem": "breq1",
            "ground_truth": "breq1 \u22a2 ( z = ( `' H ` x ) \u2192 ( z R w \u2194 ( `' H ` x ) R w ) )",
            "ground_truth_display": false,
            "statement_depth": 0,
            "_thrs_random_uniform": 0.33412,
            "_thrs_reconstruct": 0.0002,
            "_thrs_obviousness": 4e-05,
            "_thrs_weight": 0.85366,
            "_thrs_complexity": 0.71429,
            "_thrs_surprisingness": 0.15826,
            "_thrs_intensity": 0.04821,
            "_thrs_interestingness": 0.35489,
            "_thrs_logistic_regression": 0.79543,
            "_thrs_random_forest": 0.485
        },
        {
            "expression": "\u22a2 ( H : A -1-1-onto\u2192 B \u2192 ( \u2203 z \u2208 A \u2203 w \u2208 A ( ( x = ( H ` z ) \u2227 y = ( H ` w ) ) \u2227 z R w ) \u2192 ( ( x \u2208 B \u2227 y \u2208 B ) \u2227 ( `' H ` x ) R ( `' H ` y ) ) ) )",
            "prop_expression": "( \ud835\udf11 \u2192 ( ( x \u2208 A \u2227 y \u2208 B ) \u2192 ( \ud835\udf13 \u2192 \ud835\udf12 ) ) ) \u22a2 ( \ud835\udf11 \u2192 ( \u2203 x \u2208 A \u2203 y \u2208 B \ud835\udf13 \u2192 \ud835\udf12 ) )",
            "step": 35,
            "theorem": "rexlimdvv",
            "ground_truth": "rexlimdvv \u22a2 ( H : A -1-1-onto\u2192 B \u2192 ( \u2203 z \u2208 A \u2203 w \u2208 A ( ( x = ( H ` z ) \u2227 y = ( H ` w ) ) \u2227 z R w ) \u2192 ( ( x \u2208 B \u2227 y \u2208 B ) \u2227 ( `' H ` x ) R ( `' H ` y ) ) ) )",
            "ground_truth_display": false,
            "statement_depth": 0,
            "_thrs_random_uniform": 0.80628,
            "_thrs_reconstruct": 0.0,
            "_thrs_obviousness": 0.39238,
            "_thrs_weight": 0.31707,
            "_thrs_complexity": 0.0,
            "_thrs_surprisingness": 0.83864,
            "_thrs_intensity": 0.2089,
            "_thrs_interestingness": 0.3514,
            "_thrs_logistic_regression": 0.98772,
            "_thrs_random_forest": 0.865
        },
        {
            "expression": "\u22a2 ( H : A -1-1-onto\u2192 B \u2192 ( ( z \u2208 A \u2227 w \u2208 A ) \u2192 ( ( ( x = ( H ` z ) \u2227 y = ( H ` w ) ) \u2227 z R w ) \u2192 ( ( x \u2208 B \u2227 y \u2208 B ) \u2227 ( `' H ` x ) R ( `' H ` y ) ) ) ) )",
            "prop_expression": "( ( \ud835\udf11 \u2227 \ud835\udf13 \u2227 \ud835\udf12 ) \u2192 \ud835\udf03 ) \u22a2 ( \ud835\udf11 \u2192 ( \ud835\udf13 \u2192 ( \ud835\udf12 \u2192 \ud835\udf03 ) ) )",
            "step": 36,
            "theorem": "3exp",
            "ground_truth": "3exp \u22a2 ( H : A -1-1-onto\u2192 B \u2192 ( ( z \u2208 A \u2227 w \u2208 A ) \u2192 ( ( ( x = ( H ` z ) \u2227 y = ( H ` w ) ) \u2227 z R w ) \u2192 ( ( x \u2208 B \u2227 y \u2208 B ) \u2227 ( `' H ` x ) R ( `' H ` y ) ) ) ) )",
            "ground_truth_display": false,
            "statement_depth": 0,
            "_thrs_random_uniform": 0.98709,
            "_thrs_reconstruct": 0.0,
            "_thrs_obviousness": 0.39238,
            "_thrs_weight": 0.31707,
            "_thrs_complexity": 0.0,
            "_thrs_surprisingness": 0.83864,
            "_thrs_intensity": 0.2089,
            "_thrs_interestingness": 0.3514,
            "_thrs_logistic_regression": 0.98772,
            "_thrs_random_forest": 0.775
        },
        {
            "expression": "\u22a2 ( ( H : A -1-1-onto\u2192 B \u2227 ( z \u2208 A \u2227 w \u2208 A ) \u2227 ( ( x = ( H ` z ) \u2227 y = ( H ` w ) ) \u2227 z R w ) ) \u2192 ( ( x \u2208 B \u2227 y \u2208 B ) \u2227 ( `' H ` x ) R ( `' H ` y ) ) )",
            "prop_expression": "( \ud835\udf11 \u2192 \ud835\udf13 ), ( \ud835\udf11 \u2192 \ud835\udf12 ), ( \ud835\udf11 \u2192 \ud835\udf03 ) \u22a2 ( \ud835\udf11 \u2192 ( ( \ud835\udf13 \u2227 \ud835\udf12 ) \u2227 \ud835\udf03 ) )",
            "step": 37,
            "theorem": "jca31",
            "ground_truth": "jca31 \u22a2 ( ( H : A -1-1-onto\u2192 B \u2227 ( z \u2208 A \u2227 w \u2208 A ) \u2227 ( ( x = ( H ` z ) \u2227 y = ( H ` w ) ) \u2227 z R w ) ) \u2192 ( ( x \u2208 B \u2227 y \u2208 B ) \u2227 ( `' H ` x ) R ( `' H ` y ) ) )",
            "ground_truth_display": false,
            "statement_depth": 0,
            "_thrs_random_uniform": 0.12357,
            "_thrs_reconstruct": 0.0,
            "_thrs_obviousness": 0.39238,
            "_thrs_weight": 0.31707,
            "_thrs_complexity": 0.0,
            "_thrs_surprisingness": 0.83864,
            "_thrs_intensity": 0.58385,
            "_thrs_interestingness": 0.42639,
            "_thrs_logistic_regression": 0.99836,
            "_thrs_random_forest": 0.875
        },
        {
            "expression": "\u22a2 ( ( H : A -1-1-onto\u2192 B \u2227 ( z \u2208 A \u2227 w \u2208 A ) \u2227 ( ( x = ( H ` z ) \u2227 y = ( H ` w ) ) \u2227 z R w ) ) \u2192 x \u2208 B )",
            "prop_expression": "( \ud835\udf11 \u2192 A = B ), ( \ud835\udf11 \u2192 B \u2208 C ) \u22a2 ( \ud835\udf11 \u2192 A \u2208 C )",
            "step": 38,
            "theorem": "eqeltrd",
            "ground_truth": "eqeltrd \u22a2 ( ( H : A -1-1-onto\u2192 B \u2227 ( z \u2208 A \u2227 w \u2208 A ) \u2227 ( ( x = ( H ` z ) \u2227 y = ( H ` w ) ) \u2227 z R w ) ) \u2192 x \u2208 B )",
            "ground_truth_display": false,
            "statement_depth": 0,
            "_thrs_random_uniform": 0.21307,
            "_thrs_reconstruct": 0.0,
            "_thrs_obviousness": 0.05138,
            "_thrs_weight": 0.60976,
            "_thrs_complexity": 0.14286,
            "_thrs_surprisingness": 0.34689,
            "_thrs_intensity": 0.57046,
            "_thrs_interestingness": 0.34427,
            "_thrs_logistic_regression": 0.99862,
            "_thrs_random_forest": 0.845
        },
        {
            "expression": "\u22a2 ( ( H : A -1-1-onto\u2192 B \u2227 ( z \u2208 A \u2227 w \u2208 A ) \u2227 ( ( x = ( H ` z ) \u2227 y = ( H ` w ) ) \u2227 z R w ) ) \u2192 x = ( H ` z ) )",
            "prop_expression": " \u22a2 ( ( \ud835\udf03 \u2227 \ud835\udf0f \u2227 ( ( \ud835\udf11 \u2227 \ud835\udf13 ) \u2227 \ud835\udf12 ) ) \u2192 \ud835\udf11 )",
            "step": 39,
            "theorem": "simp3ll",
            "ground_truth": "simp3ll \u22a2 ( ( H : A -1-1-onto\u2192 B \u2227 ( z \u2208 A \u2227 w \u2208 A ) \u2227 ( ( x = ( H ` z ) \u2227 y = ( H ` w ) ) \u2227 z R w ) ) \u2192 x = ( H ` z ) )",
            "ground_truth_display": false,
            "statement_depth": 0,
            "_thrs_random_uniform": 0.75503,
            "_thrs_reconstruct": 0.0,
            "_thrs_obviousness": 0.0,
            "_thrs_weight": 0.58537,
            "_thrs_complexity": 0.14286,
            "_thrs_surprisingness": 0.34689,
            "_thrs_intensity": 0.02892,
            "_thrs_interestingness": 0.22081,
            "_thrs_logistic_regression": 0.97457,
            "_thrs_random_forest": 0.605
        },
        {
            "expression": "\u22a2 ( ( H : A -1-1-onto\u2192 B \u2227 ( z \u2208 A \u2227 w \u2208 A ) \u2227 ( ( x = ( H ` z ) \u2227 y = ( H ` w ) ) \u2227 z R w ) ) \u2192 ( H ` z ) \u2208 B )",
            "prop_expression": "( \ud835\udf11 \u2192 \ud835\udf13 ), ( \ud835\udf11 \u2192 \ud835\udf12 ), ( ( \ud835\udf13 \u2227 \ud835\udf12 ) \u2192 \ud835\udf03 ) \u22a2 ( \ud835\udf11 \u2192 \ud835\udf03 )",
            "step": 40,
            "theorem": "syl2anc",
            "ground_truth": "syl2anc \u22a2 ( ( H : A -1-1-onto\u2192 B \u2227 ( z \u2208 A \u2227 w \u2208 A ) \u2227 ( ( x = ( H ` z ) \u2227 y = ( H ` w ) ) \u2227 z R w ) ) \u2192 ( H ` z ) \u2208 B )",
            "ground_truth_display": false,
            "statement_depth": 0,
            "_thrs_random_uniform": 0.21369,
            "_thrs_reconstruct": 0.0,
            "_thrs_obviousness": 0.05138,
            "_thrs_weight": 0.56098,
            "_thrs_complexity": 0.14286,
            "_thrs_surprisingness": 0.34689,
            "_thrs_intensity": 0.64153,
            "_thrs_interestingness": 0.34873,
            "_thrs_logistic_regression": 0.99902,
            "_thrs_random_forest": 0.775
        },
        {
            "expression": "\u22a2 ( ( H : A -1-1-onto\u2192 B \u2227 ( z \u2208 A \u2227 w \u2208 A ) \u2227 ( ( x = ( H ` z ) \u2227 y = ( H ` w ) ) \u2227 z R w ) ) \u2192 H : A -1-1-onto\u2192 B )",
            "prop_expression": " \u22a2 ( ( \ud835\udf11 \u2227 \ud835\udf13 \u2227 \ud835\udf12 ) \u2192 \ud835\udf11 )",
            "step": 41,
            "theorem": "simp1",
            "ground_truth": "simp1 \u22a2 ( ( H : A -1-1-onto\u2192 B \u2227 ( z \u2208 A \u2227 w \u2208 A ) \u2227 ( ( x = ( H ` z ) \u2227 y = ( H ` w ) ) \u2227 z R w ) ) \u2192 H : A -1-1-onto\u2192 B )",
            "ground_truth_display": false,
            "statement_depth": 0,
            "_thrs_random_uniform": 0.48363,
            "_thrs_reconstruct": 0.0,
            "_thrs_obviousness": 0.0,
            "_thrs_weight": 0.58537,
            "_thrs_complexity": 0.14286,
            "_thrs_surprisingness": 0.34689,
            "_thrs_intensity": 0.02892,
            "_thrs_interestingness": 0.22081,
            "_thrs_logistic_regression": 0.97457,
            "_thrs_random_forest": 0.585
        },
        {
            "expression": "\u22a2 ( ( H : A -1-1-onto\u2192 B \u2227 ( z \u2208 A \u2227 w \u2208 A ) \u2227 ( ( x = ( H ` z ) \u2227 y = ( H ` w ) ) \u2227 z R w ) ) \u2192 z \u2208 A )",
            "prop_expression": " \u22a2 ( ( \ud835\udf11 \u2227 ( \ud835\udf13 \u2227 \ud835\udf12 ) \u2227 \ud835\udf03 ) \u2192 \ud835\udf13 )",
            "step": 42,
            "theorem": "simp2l",
            "ground_truth": "simp2l \u22a2 ( ( H : A -1-1-onto\u2192 B \u2227 ( z \u2208 A \u2227 w \u2208 A ) \u2227 ( ( x = ( H ` z ) \u2227 y = ( H ` w ) ) \u2227 z R w ) ) \u2192 z \u2208 A )",
            "ground_truth_display": false,
            "statement_depth": 0,
            "_thrs_random_uniform": 0.22236,
            "_thrs_reconstruct": 0.0,
            "_thrs_obviousness": 0.0,
            "_thrs_weight": 0.60976,
            "_thrs_complexity": 0.14286,
            "_thrs_surprisingness": 0.34689,
            "_thrs_intensity": 0.03482,
            "_thrs_interestingness": 0.22686,
            "_thrs_logistic_regression": 0.9759,
            "_thrs_random_forest": 0.64
        },
        {
            "expression": "\u22a2 ( ( H : A -1-1-onto\u2192 B \u2227 z \u2208 A ) \u2192 ( H ` z ) \u2208 B )",
            "prop_expression": "( \ud835\udf11 \u2192 \ud835\udf13 ), ( ( \ud835\udf13 \u2227 \ud835\udf12 ) \u2192 \ud835\udf03 ) \u22a2 ( ( \ud835\udf11 \u2227 \ud835\udf12 ) \u2192 \ud835\udf03 )",
            "step": 43,
            "theorem": "sylan",
            "ground_truth": "sylan \u22a2 ( ( H : A -1-1-onto\u2192 B \u2227 z \u2208 A ) \u2192 ( H ` z ) \u2208 B )",
            "ground_truth_display": false,
            "statement_depth": 0,
            "_thrs_random_uniform": 0.35945,
            "_thrs_reconstruct": 0.0,
            "_thrs_obviousness": 0.05138,
            "_thrs_weight": 0.90244,
            "_thrs_complexity": 0.71429,
            "_thrs_surprisingness": 0.10429,
            "_thrs_intensity": 0.3562,
            "_thrs_interestingness": 0.42572,
            "_thrs_logistic_regression": 0.95831,
            "_thrs_random_forest": 0.765
        },
        {
            "expression": "\u22a2 ( H : A -1-1-onto\u2192 B \u2192 H : A -\u2192 B )",
            "prop_expression": " \u22a2 ( F : A -1-1-onto\u2192 B \u2192 F : A -\u2192 B )",
            "step": 44,
            "theorem": "f1of",
            "ground_truth": "f1of \u22a2 ( H : A -1-1-onto\u2192 B \u2192 H : A -\u2192 B )",
            "ground_truth_display": false,
            "statement_depth": 0,
            "_thrs_random_uniform": 0.0196,
            "_thrs_reconstruct": 0.0,
            "_thrs_obviousness": 0.0,
            "_thrs_weight": 1.0,
            "_thrs_complexity": 1.0,
            "_thrs_surprisingness": 0.29631,
            "_thrs_intensity": 0.08838,
            "_thrs_interestingness": 0.47694,
            "_thrs_logistic_regression": 0.51887,
            "_thrs_random_forest": 0.665
        },
        {
            "expression": "\u22a2 ( ( H : A -\u2192 B \u2227 z \u2208 A ) \u2192 ( H ` z ) \u2208 B )",
            "prop_expression": " \u22a2 ( ( F : A -\u2192 B \u2227 C \u2208 A ) \u2192 ( F ` C ) \u2208 B )",
            "step": 45,
            "theorem": "ffvelrn",
            "ground_truth": "ffvelrn \u22a2 ( ( H : A -\u2192 B \u2227 z \u2208 A ) \u2192 ( H ` z ) \u2208 B )",
            "ground_truth_display": false,
            "statement_depth": 0,
            "_thrs_random_uniform": 0.23066,
            "_thrs_reconstruct": 0.23912,
            "_thrs_obviousness": 0.05138,
            "_thrs_weight": 0.90244,
            "_thrs_complexity": 0.71429,
            "_thrs_surprisingness": 0.44861,
            "_thrs_intensity": 0.07499,
            "_thrs_interestingness": 0.43834,
            "_thrs_logistic_regression": 0.75976,
            "_thrs_random_forest": 0.725
        },
        {
            "expression": "\u22a2 ( ( H : A -1-1-onto\u2192 B \u2227 ( z \u2208 A \u2227 w \u2208 A ) \u2227 ( ( x = ( H ` z ) \u2227 y = ( H ` w ) ) \u2227 z R w ) ) \u2192 y \u2208 B )",
            "prop_expression": "( \ud835\udf11 \u2192 A = B ), ( \ud835\udf11 \u2192 B \u2208 C ) \u22a2 ( \ud835\udf11 \u2192 A \u2208 C )",
            "step": 46,
            "theorem": "eqeltrd",
            "ground_truth": "eqeltrd \u22a2 ( ( H : A -1-1-onto\u2192 B \u2227 ( z \u2208 A \u2227 w \u2208 A ) \u2227 ( ( x = ( H ` z ) \u2227 y = ( H ` w ) ) \u2227 z R w ) ) \u2192 y \u2208 B )",
            "ground_truth_display": false,
            "statement_depth": 0,
            "_thrs_random_uniform": 0.19243,
            "_thrs_reconstruct": 0.0,
            "_thrs_obviousness": 0.05138,
            "_thrs_weight": 0.60976,
            "_thrs_complexity": 0.14286,
            "_thrs_surprisingness": 0.34689,
            "_thrs_intensity": 0.57046,
            "_thrs_interestingness": 0.34427,
            "_thrs_logistic_regression": 0.99862,
            "_thrs_random_forest": 0.845
        },
        {
            "expression": "\u22a2 ( ( H : A -1-1-onto\u2192 B \u2227 ( z \u2208 A \u2227 w \u2208 A ) \u2227 ( ( x = ( H ` z ) \u2227 y = ( H ` w ) ) \u2227 z R w ) ) \u2192 y = ( H ` w ) )",
            "prop_expression": " \u22a2 ( ( \ud835\udf03 \u2227 \ud835\udf0f \u2227 ( ( \ud835\udf11 \u2227 \ud835\udf13 ) \u2227 \ud835\udf12 ) ) \u2192 \ud835\udf13 )",
            "step": 47,
            "theorem": "simp3lr",
            "ground_truth": "simp3lr \u22a2 ( ( H : A -1-1-onto\u2192 B \u2227 ( z \u2208 A \u2227 w \u2208 A ) \u2227 ( ( x = ( H ` z ) \u2227 y = ( H ` w ) ) \u2227 z R w ) ) \u2192 y = ( H ` w ) )",
            "ground_truth_display": false,
            "statement_depth": 0,
            "_thrs_random_uniform": 0.43791,
            "_thrs_reconstruct": 0.0,
            "_thrs_obviousness": 0.0,
            "_thrs_weight": 0.58537,
            "_thrs_complexity": 0.14286,
            "_thrs_surprisingness": 0.34689,
            "_thrs_intensity": 0.02892,
            "_thrs_interestingness": 0.22081,
            "_thrs_logistic_regression": 0.97457,
            "_thrs_random_forest": 0.605
        },
        {
            "expression": "\u22a2 ( ( H : A -1-1-onto\u2192 B \u2227 ( z \u2208 A \u2227 w \u2208 A ) \u2227 ( ( x = ( H ` z ) \u2227 y = ( H ` w ) ) \u2227 z R w ) ) \u2192 ( H ` w ) \u2208 B )",
            "prop_expression": "( \ud835\udf11 \u2192 \ud835\udf13 ), ( \ud835\udf11 \u2192 \ud835\udf12 ), ( ( \ud835\udf13 \u2227 \ud835\udf12 ) \u2192 \ud835\udf03 ) \u22a2 ( \ud835\udf11 \u2192 \ud835\udf03 )",
            "step": 48,
            "theorem": "syl2anc",
            "ground_truth": "syl2anc \u22a2 ( ( H : A -1-1-onto\u2192 B \u2227 ( z \u2208 A \u2227 w \u2208 A ) \u2227 ( ( x = ( H ` z ) \u2227 y = ( H ` w ) ) \u2227 z R w ) ) \u2192 ( H ` w ) \u2208 B )",
            "ground_truth_display": false,
            "statement_depth": 0,
            "_thrs_random_uniform": 0.33964,
            "_thrs_reconstruct": 0.0,
            "_thrs_obviousness": 0.05138,
            "_thrs_weight": 0.56098,
            "_thrs_complexity": 0.14286,
            "_thrs_surprisingness": 0.34689,
            "_thrs_intensity": 0.64153,
            "_thrs_interestingness": 0.34873,
            "_thrs_logistic_regression": 0.99902,
            "_thrs_random_forest": 0.775
        },
        {
            "expression": "\u22a2 ( ( H : A -1-1-onto\u2192 B \u2227 ( z \u2208 A \u2227 w \u2208 A ) \u2227 ( ( x = ( H ` z ) \u2227 y = ( H ` w ) ) \u2227 z R w ) ) \u2192 H : A -1-1-onto\u2192 B )",
            "prop_expression": " \u22a2 ( ( \ud835\udf11 \u2227 \ud835\udf13 \u2227 \ud835\udf12 ) \u2192 \ud835\udf11 )",
            "step": 49,
            "theorem": "simp1",
            "ground_truth": "simp1 \u22a2 ( ( H : A -1-1-onto\u2192 B \u2227 ( z \u2208 A \u2227 w \u2208 A ) \u2227 ( ( x = ( H ` z ) \u2227 y = ( H ` w ) ) \u2227 z R w ) ) \u2192 H : A -1-1-onto\u2192 B )",
            "ground_truth_display": false,
            "statement_depth": 0,
            "_thrs_random_uniform": 0.72883,
            "_thrs_reconstruct": 0.0,
            "_thrs_obviousness": 0.0,
            "_thrs_weight": 0.58537,
            "_thrs_complexity": 0.14286,
            "_thrs_surprisingness": 0.34689,
            "_thrs_intensity": 0.02892,
            "_thrs_interestingness": 0.22081,
            "_thrs_logistic_regression": 0.97457,
            "_thrs_random_forest": 0.585
        },
        {
            "expression": "\u22a2 ( ( H : A -1-1-onto\u2192 B \u2227 ( z \u2208 A \u2227 w \u2208 A ) \u2227 ( ( x = ( H ` z ) \u2227 y = ( H ` w ) ) \u2227 z R w ) ) \u2192 w \u2208 A )",
            "prop_expression": " \u22a2 ( ( \ud835\udf11 \u2227 ( \ud835\udf13 \u2227 \ud835\udf12 ) \u2227 \ud835\udf03 ) \u2192 \ud835\udf12 )",
            "step": 50,
            "theorem": "simp2r",
            "ground_truth": "simp2r \u22a2 ( ( H : A -1-1-onto\u2192 B \u2227 ( z \u2208 A \u2227 w \u2208 A ) \u2227 ( ( x = ( H ` z ) \u2227 y = ( H ` w ) ) \u2227 z R w ) ) \u2192 w \u2208 A )",
            "ground_truth_display": false,
            "statement_depth": 0,
            "_thrs_random_uniform": 0.37698,
            "_thrs_reconstruct": 0.0,
            "_thrs_obviousness": 0.0,
            "_thrs_weight": 0.60976,
            "_thrs_complexity": 0.14286,
            "_thrs_surprisingness": 0.34689,
            "_thrs_intensity": 0.03482,
            "_thrs_interestingness": 0.22686,
            "_thrs_logistic_regression": 0.9759,
            "_thrs_random_forest": 0.64
        },
        {
            "expression": "\u22a2 ( ( H : A -1-1-onto\u2192 B \u2227 w \u2208 A ) \u2192 ( H ` w ) \u2208 B )",
            "prop_expression": "( \ud835\udf11 \u2192 \ud835\udf13 ), ( ( \ud835\udf13 \u2227 \ud835\udf12 ) \u2192 \ud835\udf03 ) \u22a2 ( ( \ud835\udf11 \u2227 \ud835\udf12 ) \u2192 \ud835\udf03 )",
            "step": 51,
            "theorem": "sylan",
            "ground_truth": "sylan \u22a2 ( ( H : A -1-1-onto\u2192 B \u2227 w \u2208 A ) \u2192 ( H ` w ) \u2208 B )",
            "ground_truth_display": false,
            "statement_depth": 0,
            "_thrs_random_uniform": 0.39394,
            "_thrs_reconstruct": 0.0,
            "_thrs_obviousness": 0.05138,
            "_thrs_weight": 0.90244,
            "_thrs_complexity": 0.71429,
            "_thrs_surprisingness": 0.10429,
            "_thrs_intensity": 0.3562,
            "_thrs_interestingness": 0.42572,
            "_thrs_logistic_regression": 0.95831,
            "_thrs_random_forest": 0.765
        },
        {
            "expression": "\u22a2 ( H : A -1-1-onto\u2192 B \u2192 H : A -\u2192 B )",
            "prop_expression": " \u22a2 ( F : A -1-1-onto\u2192 B \u2192 F : A -\u2192 B )",
            "step": 52,
            "theorem": "f1of",
            "ground_truth": "f1of \u22a2 ( H : A -1-1-onto\u2192 B \u2192 H : A -\u2192 B )",
            "ground_truth_display": false,
            "statement_depth": 0,
            "_thrs_random_uniform": 0.94699,
            "_thrs_reconstruct": 0.0,
            "_thrs_obviousness": 0.0,
            "_thrs_weight": 1.0,
            "_thrs_complexity": 1.0,
            "_thrs_surprisingness": 0.29631,
            "_thrs_intensity": 0.08838,
            "_thrs_interestingness": 0.47694,
            "_thrs_logistic_regression": 0.51887,
            "_thrs_random_forest": 0.665
        },
        {
            "expression": "\u22a2 ( ( H : A -\u2192 B \u2227 w \u2208 A ) \u2192 ( H ` w ) \u2208 B )",
            "prop_expression": " \u22a2 ( ( F : A -\u2192 B \u2227 C \u2208 A ) \u2192 ( F ` C ) \u2208 B )",
            "step": 53,
            "theorem": "ffvelrn",
            "ground_truth": "ffvelrn \u22a2 ( ( H : A -\u2192 B \u2227 w \u2208 A ) \u2192 ( H ` w ) \u2208 B )",
            "ground_truth_display": false,
            "statement_depth": 0,
            "_thrs_random_uniform": 0.5214,
            "_thrs_reconstruct": 0.23912,
            "_thrs_obviousness": 0.05138,
            "_thrs_weight": 0.90244,
            "_thrs_complexity": 0.71429,
            "_thrs_surprisingness": 0.44861,
            "_thrs_intensity": 0.07499,
            "_thrs_interestingness": 0.43834,
            "_thrs_logistic_regression": 0.75976,
            "_thrs_random_forest": 0.725
        },
        {
            "expression": "\u22a2 ( ( H : A -1-1-onto\u2192 B \u2227 ( z \u2208 A \u2227 w \u2208 A ) \u2227 ( ( x = ( H ` z ) \u2227 y = ( H ` w ) ) \u2227 z R w ) ) \u2192 ( `' H ` x ) R ( `' H ` y ) )",
            "prop_expression": "( \ud835\udf11 \u2192 A R B ), ( \ud835\udf11 \u2192 C = A ), ( \ud835\udf11 \u2192 D = B ) \u22a2 ( \ud835\udf11 \u2192 C R D )",
            "step": 54,
            "theorem": "3brtr4d",
            "ground_truth": "3brtr4d \u22a2 ( ( H : A -1-1-onto\u2192 B \u2227 ( z \u2208 A \u2227 w \u2208 A ) \u2227 ( ( x = ( H ` z ) \u2227 y = ( H ` w ) ) \u2227 z R w ) ) \u2192 ( `' H ` x ) R ( `' H ` y ) )",
            "ground_truth_display": false,
            "statement_depth": 0,
            "_thrs_random_uniform": 0.45058,
            "_thrs_reconstruct": 0.0004,
            "_thrs_obviousness": 0.28961,
            "_thrs_weight": 0.46341,
            "_thrs_complexity": 0.0,
            "_thrs_surprisingness": 0.83864,
            "_thrs_intensity": 0.70169,
            "_thrs_interestingness": 0.45867,
            "_thrs_logistic_regression": 0.99925,
            "_thrs_random_forest": 0.815
        },
        {
            "expression": "\u22a2 ( ( H : A -1-1-onto\u2192 B \u2227 ( z \u2208 A \u2227 w \u2208 A ) \u2227 ( ( x = ( H ` z ) \u2227 y = ( H ` w ) ) \u2227 z R w ) ) \u2192 z R w )",
            "prop_expression": " \u22a2 ( ( \ud835\udf11 \u2227 \ud835\udf13 \u2227 ( \ud835\udf12 \u2227 \ud835\udf03 ) ) \u2192 \ud835\udf03 )",
            "step": 55,
            "theorem": "simp3r",
            "ground_truth": "simp3r \u22a2 ( ( H : A -1-1-onto\u2192 B \u2227 ( z \u2208 A \u2227 w \u2208 A ) \u2227 ( ( x = ( H ` z ) \u2227 y = ( H ` w ) ) \u2227 z R w ) ) \u2192 z R w )",
            "ground_truth_display": false,
            "statement_depth": 0,
            "_thrs_random_uniform": 0.92078,
            "_thrs_reconstruct": 0.0,
            "_thrs_obviousness": 0.0,
            "_thrs_weight": 0.60976,
            "_thrs_complexity": 0.14286,
            "_thrs_surprisingness": 0.34689,
            "_thrs_intensity": 0.03482,
            "_thrs_interestingness": 0.22686,
            "_thrs_logistic_regression": 0.9759,
            "_thrs_random_forest": 0.755
        },
        {
            "expression": "\u22a2 ( ( H : A -1-1-onto\u2192 B \u2227 ( z \u2208 A \u2227 w \u2208 A ) \u2227 ( ( x = ( H ` z ) \u2227 y = ( H ` w ) ) \u2227 z R w ) ) \u2192 ( `' H ` x ) = z )",
            "prop_expression": "( \ud835\udf11 \u2192 \ud835\udf13 ), ( \ud835\udf11 \u2192 ( \ud835\udf13 \u2192 \ud835\udf12 ) ) \u22a2 ( \ud835\udf11 \u2192 \ud835\udf12 )",
            "step": 56,
            "theorem": "mpd",
            "ground_truth": "mpd \u22a2 ( ( H : A -1-1-onto\u2192 B \u2227 ( z \u2208 A \u2227 w \u2208 A ) \u2227 ( ( x = ( H ` z ) \u2227 y = ( H ` w ) ) \u2227 z R w ) ) \u2192 ( `' H ` x ) = z )",
            "ground_truth_display": false,
            "statement_depth": 0,
            "_thrs_random_uniform": 0.49008,
            "_thrs_reconstruct": 0.0,
            "_thrs_obviousness": 0.14476,
            "_thrs_weight": 0.56098,
            "_thrs_complexity": 0.0,
            "_thrs_surprisingness": 0.83864,
            "_thrs_intensity": 0.56737,
            "_thrs_interestingness": 0.42235,
            "_thrs_logistic_regression": 0.99861,
            "_thrs_random_forest": 0.83
        },
        {
            "expression": "\u22a2 ( ( H : A -1-1-onto\u2192 B \u2227 ( z \u2208 A \u2227 w \u2208 A ) \u2227 ( ( x = ( H ` z ) \u2227 y = ( H ` w ) ) \u2227 z R w ) ) \u2192 ( H ` z ) = x )",
            "prop_expression": "( \ud835\udf11 \u2192 A = B ) \u22a2 ( \ud835\udf11 \u2192 B = A )",
            "step": 57,
            "theorem": "eqcomd",
            "ground_truth": "eqcomd \u22a2 ( ( H : A -1-1-onto\u2192 B \u2227 ( z \u2208 A \u2227 w \u2208 A ) \u2227 ( ( x = ( H ` z ) \u2227 y = ( H ` w ) ) \u2227 z R w ) ) \u2192 ( H ` z ) = x )",
            "ground_truth_display": false,
            "statement_depth": 0,
            "_thrs_random_uniform": 0.17472,
            "_thrs_reconstruct": 0.0,
            "_thrs_obviousness": 0.0,
            "_thrs_weight": 0.58537,
            "_thrs_complexity": 0.14286,
            "_thrs_surprisingness": 0.34689,
            "_thrs_intensity": 0.2089,
            "_thrs_interestingness": 0.2568,
            "_thrs_logistic_regression": 0.99022,
            "_thrs_random_forest": 0.8
        },
        {
            "expression": "\u22a2 ( ( H : A -1-1-onto\u2192 B \u2227 ( z \u2208 A \u2227 w \u2208 A ) \u2227 ( ( x = ( H ` z ) \u2227 y = ( H ` w ) ) \u2227 z R w ) ) \u2192 x = ( H ` z ) )",
            "prop_expression": " \u22a2 ( ( \ud835\udf03 \u2227 \ud835\udf0f \u2227 ( ( \ud835\udf11 \u2227 \ud835\udf13 ) \u2227 \ud835\udf12 ) ) \u2192 \ud835\udf11 )",
            "step": 58,
            "theorem": "simp3ll",
            "ground_truth": "simp3ll \u22a2 ( ( H : A -1-1-onto\u2192 B \u2227 ( z \u2208 A \u2227 w \u2208 A ) \u2227 ( ( x = ( H ` z ) \u2227 y = ( H ` w ) ) \u2227 z R w ) ) \u2192 x = ( H ` z ) )",
            "ground_truth_display": false,
            "statement_depth": 0,
            "_thrs_random_uniform": 0.57101,
            "_thrs_reconstruct": 0.0,
            "_thrs_obviousness": 0.0,
            "_thrs_weight": 0.58537,
            "_thrs_complexity": 0.14286,
            "_thrs_surprisingness": 0.34689,
            "_thrs_intensity": 0.02892,
            "_thrs_interestingness": 0.22081,
            "_thrs_logistic_regression": 0.97457,
            "_thrs_random_forest": 0.51
        },
        {
            "expression": "\u22a2 ( ( H : A -1-1-onto\u2192 B \u2227 ( z \u2208 A \u2227 w \u2208 A ) \u2227 ( ( x = ( H ` z ) \u2227 y = ( H ` w ) ) \u2227 z R w ) ) \u2192 ( ( H ` z ) = x \u2192 ( `' H ` x ) = z ) )",
            "prop_expression": "( \ud835\udf11 \u2192 \ud835\udf13 ), ( \ud835\udf11 \u2192 \ud835\udf12 ), ( ( \ud835\udf13 \u2227 \ud835\udf12 ) \u2192 \ud835\udf03 ) \u22a2 ( \ud835\udf11 \u2192 \ud835\udf03 )",
            "step": 59,
            "theorem": "syl2anc",
            "ground_truth": "syl2anc \u22a2 ( ( H : A -1-1-onto\u2192 B \u2227 ( z \u2208 A \u2227 w \u2208 A ) \u2227 ( ( x = ( H ` z ) \u2227 y = ( H ` w ) ) \u2227 z R w ) ) \u2192 ( ( H ` z ) = x \u2192 ( `' H ` x ) = z ) )",
            "ground_truth_display": false,
            "statement_depth": 0,
            "_thrs_random_uniform": 0.83267,
            "_thrs_reconstruct": 0.0,
            "_thrs_obviousness": 0.14476,
            "_thrs_weight": 0.46341,
            "_thrs_complexity": 0.0,
            "_thrs_surprisingness": 0.83864,
            "_thrs_intensity": 0.58385,
            "_thrs_interestingness": 0.40613,
            "_thrs_logistic_regression": 0.9986,
            "_thrs_random_forest": 0.825
        },
        {
            "expression": "\u22a2 ( ( H : A -1-1-onto\u2192 B \u2227 ( z \u2208 A \u2227 w \u2208 A ) \u2227 ( ( x = ( H ` z ) \u2227 y = ( H ` w ) ) \u2227 z R w ) ) \u2192 H : A -1-1-onto\u2192 B )",
            "prop_expression": " \u22a2 ( ( \ud835\udf11 \u2227 \ud835\udf13 \u2227 \ud835\udf12 ) \u2192 \ud835\udf11 )",
            "step": 60,
            "theorem": "simp1",
            "ground_truth": "simp1 \u22a2 ( ( H : A -1-1-onto\u2192 B \u2227 ( z \u2208 A \u2227 w \u2208 A ) \u2227 ( ( x = ( H ` z ) \u2227 y = ( H ` w ) ) \u2227 z R w ) ) \u2192 H : A -1-1-onto\u2192 B )",
            "ground_truth_display": false,
            "statement_depth": 0,
            "_thrs_random_uniform": 0.49513,
            "_thrs_reconstruct": 0.0,
            "_thrs_obviousness": 0.0,
            "_thrs_weight": 0.58537,
            "_thrs_complexity": 0.14286,
            "_thrs_surprisingness": 0.34689,
            "_thrs_intensity": 0.02892,
            "_thrs_interestingness": 0.22081,
            "_thrs_logistic_regression": 0.97457,
            "_thrs_random_forest": 0.7
        },
        {
            "expression": "\u22a2 ( ( H : A -1-1-onto\u2192 B \u2227 ( z \u2208 A \u2227 w \u2208 A ) \u2227 ( ( x = ( H ` z ) \u2227 y = ( H ` w ) ) \u2227 z R w ) ) \u2192 z \u2208 A )",
            "prop_expression": " \u22a2 ( ( \ud835\udf11 \u2227 ( \ud835\udf13 \u2227 \ud835\udf12 ) \u2227 \ud835\udf03 ) \u2192 \ud835\udf13 )",
            "step": 61,
            "theorem": "simp2l",
            "ground_truth": "simp2l \u22a2 ( ( H : A -1-1-onto\u2192 B \u2227 ( z \u2208 A \u2227 w \u2208 A ) \u2227 ( ( x = ( H ` z ) \u2227 y = ( H ` w ) ) \u2227 z R w ) ) \u2192 z \u2208 A )",
            "ground_truth_display": false,
            "statement_depth": 0,
            "_thrs_random_uniform": 0.80965,
            "_thrs_reconstruct": 0.0,
            "_thrs_obviousness": 0.0,
            "_thrs_weight": 0.60976,
            "_thrs_complexity": 0.14286,
            "_thrs_surprisingness": 0.34689,
            "_thrs_intensity": 0.03482,
            "_thrs_interestingness": 0.22686,
            "_thrs_logistic_regression": 0.9759,
            "_thrs_random_forest": 0.785
        },
        {
            "expression": "\u22a2 ( ( H : A -1-1-onto\u2192 B \u2227 z \u2208 A ) \u2192 ( ( H ` z ) = x \u2192 ( `' H ` x ) = z ) )",
            "prop_expression": " \u22a2 ( ( F : A -1-1-onto\u2192 B \u2227 C \u2208 A ) \u2192 ( ( F ` C ) = D \u2192 ( `' F ` D ) = C ) )",
            "step": 62,
            "theorem": "f1ocnvfv",
            "ground_truth": "f1ocnvfv \u22a2 ( ( H : A -1-1-onto\u2192 B \u2227 z \u2208 A ) \u2192 ( ( H ` z ) = x \u2192 ( `' H ` x ) = z ) )",
            "ground_truth_display": false,
            "statement_depth": 0,
            "_thrs_random_uniform": 0.8032,
            "_thrs_reconstruct": 0.67368,
            "_thrs_obviousness": 0.14476,
            "_thrs_weight": 0.80488,
            "_thrs_complexity": 0.42857,
            "_thrs_surprisingness": 0.51252,
            "_thrs_intensity": 0.06829,
            "_thrs_interestingness": 0.39181,
            "_thrs_logistic_regression": 0.91524,
            "_thrs_random_forest": 0.885
        },
        {
            "expression": "\u22a2 ( ( H : A -1-1-onto\u2192 B \u2227 ( z \u2208 A \u2227 w \u2208 A ) \u2227 ( ( x = ( H ` z ) \u2227 y = ( H ` w ) ) \u2227 z R w ) ) \u2192 ( `' H ` y ) = w )",
            "prop_expression": "( \ud835\udf11 \u2192 \ud835\udf13 ), ( \ud835\udf11 \u2192 ( \ud835\udf13 \u2192 \ud835\udf12 ) ) \u22a2 ( \ud835\udf11 \u2192 \ud835\udf12 )",
            "step": 63,
            "theorem": "mpd",
            "ground_truth": "mpd \u22a2 ( ( H : A -1-1-onto\u2192 B \u2227 ( z \u2208 A \u2227 w \u2208 A ) \u2227 ( ( x = ( H ` z ) \u2227 y = ( H ` w ) ) \u2227 z R w ) ) \u2192 ( `' H ` y ) = w )",
            "ground_truth_display": false,
            "statement_depth": 0,
            "_thrs_random_uniform": 0.93291,
            "_thrs_reconstruct": 0.0,
            "_thrs_obviousness": 0.14476,
            "_thrs_weight": 0.56098,
            "_thrs_complexity": 0.0,
            "_thrs_surprisingness": 0.83864,
            "_thrs_intensity": 0.56737,
            "_thrs_interestingness": 0.42235,
            "_thrs_logistic_regression": 0.99861,
            "_thrs_random_forest": 0.83
        },
        {
            "expression": "\u22a2 ( ( H : A -1-1-onto\u2192 B \u2227 ( z \u2208 A \u2227 w \u2208 A ) \u2227 ( ( x = ( H ` z ) \u2227 y = ( H ` w ) ) \u2227 z R w ) ) \u2192 ( H ` w ) = y )",
            "prop_expression": "( \ud835\udf11 \u2192 A = B ) \u22a2 ( \ud835\udf11 \u2192 B = A )",
            "step": 64,
            "theorem": "eqcomd",
            "ground_truth": "eqcomd \u22a2 ( ( H : A -1-1-onto\u2192 B \u2227 ( z \u2208 A \u2227 w \u2208 A ) \u2227 ( ( x = ( H ` z ) \u2227 y = ( H ` w ) ) \u2227 z R w ) ) \u2192 ( H ` w ) = y )",
            "ground_truth_display": false,
            "statement_depth": 0,
            "_thrs_random_uniform": 0.95104,
            "_thrs_reconstruct": 0.0,
            "_thrs_obviousness": 0.0,
            "_thrs_weight": 0.58537,
            "_thrs_complexity": 0.14286,
            "_thrs_surprisingness": 0.34689,
            "_thrs_intensity": 0.2089,
            "_thrs_interestingness": 0.2568,
            "_thrs_logistic_regression": 0.99022,
            "_thrs_random_forest": 0.8
        },
        {
            "expression": "\u22a2 ( ( H : A -1-1-onto\u2192 B \u2227 ( z \u2208 A \u2227 w \u2208 A ) \u2227 ( ( x = ( H ` z ) \u2227 y = ( H ` w ) ) \u2227 z R w ) ) \u2192 y = ( H ` w ) )",
            "prop_expression": " \u22a2 ( ( \ud835\udf03 \u2227 \ud835\udf0f \u2227 ( ( \ud835\udf11 \u2227 \ud835\udf13 ) \u2227 \ud835\udf12 ) ) \u2192 \ud835\udf13 )",
            "step": 65,
            "theorem": "simp3lr",
            "ground_truth": "simp3lr \u22a2 ( ( H : A -1-1-onto\u2192 B \u2227 ( z \u2208 A \u2227 w \u2208 A ) \u2227 ( ( x = ( H ` z ) \u2227 y = ( H ` w ) ) \u2227 z R w ) ) \u2192 y = ( H ` w ) )",
            "ground_truth_display": false,
            "statement_depth": 0,
            "_thrs_random_uniform": 0.33809,
            "_thrs_reconstruct": 0.0,
            "_thrs_obviousness": 0.0,
            "_thrs_weight": 0.58537,
            "_thrs_complexity": 0.14286,
            "_thrs_surprisingness": 0.34689,
            "_thrs_intensity": 0.02892,
            "_thrs_interestingness": 0.22081,
            "_thrs_logistic_regression": 0.97457,
            "_thrs_random_forest": 0.51
        },
        {
            "expression": "\u22a2 ( ( H : A -1-1-onto\u2192 B \u2227 ( z \u2208 A \u2227 w \u2208 A ) \u2227 ( ( x = ( H ` z ) \u2227 y = ( H ` w ) ) \u2227 z R w ) ) \u2192 ( ( H ` w ) = y \u2192 ( `' H ` y ) = w ) )",
            "prop_expression": "( \ud835\udf11 \u2192 \ud835\udf13 ), ( \ud835\udf11 \u2192 \ud835\udf12 ), ( ( \ud835\udf13 \u2227 \ud835\udf12 ) \u2192 \ud835\udf03 ) \u22a2 ( \ud835\udf11 \u2192 \ud835\udf03 )",
            "step": 66,
            "theorem": "syl2anc",
            "ground_truth": "syl2anc \u22a2 ( ( H : A -1-1-onto\u2192 B \u2227 ( z \u2208 A \u2227 w \u2208 A ) \u2227 ( ( x = ( H ` z ) \u2227 y = ( H ` w ) ) \u2227 z R w ) ) \u2192 ( ( H ` w ) = y \u2192 ( `' H ` y ) = w ) )",
            "ground_truth_display": false,
            "statement_depth": 0,
            "_thrs_random_uniform": 0.39294,
            "_thrs_reconstruct": 0.0,
            "_thrs_obviousness": 0.14476,
            "_thrs_weight": 0.46341,
            "_thrs_complexity": 0.0,
            "_thrs_surprisingness": 0.83864,
            "_thrs_intensity": 0.58385,
            "_thrs_interestingness": 0.40613,
            "_thrs_logistic_regression": 0.9986,
            "_thrs_random_forest": 0.825
        },
        {
            "expression": "\u22a2 ( ( H : A -1-1-onto\u2192 B \u2227 ( z \u2208 A \u2227 w \u2208 A ) \u2227 ( ( x = ( H ` z ) \u2227 y = ( H ` w ) ) \u2227 z R w ) ) \u2192 H : A -1-1-onto\u2192 B )",
            "prop_expression": " \u22a2 ( ( \ud835\udf11 \u2227 \ud835\udf13 \u2227 \ud835\udf12 ) \u2192 \ud835\udf11 )",
            "step": 67,
            "theorem": "simp1",
            "ground_truth": "simp1 \u22a2 ( ( H : A -1-1-onto\u2192 B \u2227 ( z \u2208 A \u2227 w \u2208 A ) \u2227 ( ( x = ( H ` z ) \u2227 y = ( H ` w ) ) \u2227 z R w ) ) \u2192 H : A -1-1-onto\u2192 B )",
            "ground_truth_display": false,
            "statement_depth": 0,
            "_thrs_random_uniform": 0.05426,
            "_thrs_reconstruct": 0.0,
            "_thrs_obviousness": 0.0,
            "_thrs_weight": 0.58537,
            "_thrs_complexity": 0.14286,
            "_thrs_surprisingness": 0.34689,
            "_thrs_intensity": 0.02892,
            "_thrs_interestingness": 0.22081,
            "_thrs_logistic_regression": 0.97457,
            "_thrs_random_forest": 0.7
        },
        {
            "expression": "\u22a2 ( ( H : A -1-1-onto\u2192 B \u2227 ( z \u2208 A \u2227 w \u2208 A ) \u2227 ( ( x = ( H ` z ) \u2227 y = ( H ` w ) ) \u2227 z R w ) ) \u2192 w \u2208 A )",
            "prop_expression": " \u22a2 ( ( \ud835\udf11 \u2227 ( \ud835\udf13 \u2227 \ud835\udf12 ) \u2227 \ud835\udf03 ) \u2192 \ud835\udf12 )",
            "step": 68,
            "theorem": "simp2r",
            "ground_truth": "simp2r \u22a2 ( ( H : A -1-1-onto\u2192 B \u2227 ( z \u2208 A \u2227 w \u2208 A ) \u2227 ( ( x = ( H ` z ) \u2227 y = ( H ` w ) ) \u2227 z R w ) ) \u2192 w \u2208 A )",
            "ground_truth_display": false,
            "statement_depth": 0,
            "_thrs_random_uniform": 0.73549,
            "_thrs_reconstruct": 0.0,
            "_thrs_obviousness": 0.0,
            "_thrs_weight": 0.60976,
            "_thrs_complexity": 0.14286,
            "_thrs_surprisingness": 0.34689,
            "_thrs_intensity": 0.03482,
            "_thrs_interestingness": 0.22686,
            "_thrs_logistic_regression": 0.9759,
            "_thrs_random_forest": 0.785
        },
        {
            "expression": "\u22a2 ( ( H : A -1-1-onto\u2192 B \u2227 w \u2208 A ) \u2192 ( ( H ` w ) = y \u2192 ( `' H ` y ) = w ) )",
            "prop_expression": " \u22a2 ( ( F : A -1-1-onto\u2192 B \u2227 C \u2208 A ) \u2192 ( ( F ` C ) = D \u2192 ( `' F ` D ) = C ) )",
            "step": 69,
            "theorem": "f1ocnvfv",
            "ground_truth": "f1ocnvfv \u22a2 ( ( H : A -1-1-onto\u2192 B \u2227 w \u2208 A ) \u2192 ( ( H ` w ) = y \u2192 ( `' H ` y ) = w ) )",
            "ground_truth_display": false,
            "statement_depth": 0,
            "_thrs_random_uniform": 0.23861,
            "_thrs_reconstruct": 0.67368,
            "_thrs_obviousness": 0.14476,
            "_thrs_weight": 0.80488,
            "_thrs_complexity": 0.42857,
            "_thrs_surprisingness": 0.51252,
            "_thrs_intensity": 0.06829,
            "_thrs_interestingness": 0.39181,
            "_thrs_logistic_regression": 0.91524,
            "_thrs_random_forest": 0.885
        },
        {
            "expression": "\u22a2 ( ( H : A -1-1-onto\u2192 B \u2227 S = { \u27e8 x , y \u27e9 | \u2203 z \u2208 A \u2203 w \u2208 A ( ( x = ( H ` z ) \u2227 y = ( H ` w ) ) \u2227 z R w ) } ) \u2192 H Isom R , S ( A , B ) )",
            "prop_expression": " \u22a2 ( ( H : A -1-1-onto\u2192 B \u2227 S = { \u27e8 z , w \u27e9 | \u2203 x \u2208 A \u2203 y \u2208 A ( ( z = ( H ` x ) \u2227 w = ( H ` y ) ) \u2227 x R y ) } ) \u2192 H Isom R , S ( A , B ) )",
            "step": 70,
            "theorem": "f1oiso",
            "ground_truth": "f1oiso \u22a2 ( ( H : A -1-1-onto\u2192 B \u2227 S = { \u27e8 x , y \u27e9 | \u2203 z \u2208 A \u2203 w \u2208 A ( ( x = ( H ` z ) \u2227 y = ( H ` w ) ) \u2227 z R w ) } ) \u2192 H Isom R , S ( A , B ) )",
            "ground_truth_display": false,
            "statement_depth": 0,
            "_thrs_random_uniform": 0.75455,
            "_thrs_reconstruct": 1.0,
            "_thrs_obviousness": 0.21489,
            "_thrs_weight": 0.4878,
            "_thrs_complexity": 0.0,
            "_thrs_surprisingness": 0.98952,
            "_thrs_intensity": 0.0205,
            "_thrs_interestingness": 0.34254,
            "_thrs_logistic_regression": 0.96593,
            "_thrs_random_forest": 0.955
        }
    ]
}