{
    "theorem": "sb1",
    "hyps": [
        [
            1,
            2
        ]
    ],
    "expression": "( [ y / x ] \ud835\udf11 \u2192 \u2203 x ( x = y \u2227 \ud835\udf11 ) )",
    "steps": [
        {
            "number": 1736,
            "expression": "\u22a2 ( [ y / x ] \ud835\udf11 \u2192 \u2203 x ( x = y \u2227 \ud835\udf11 ) )",
            "prop_expression": "( \ud835\udf11 \u2194 ( \ud835\udf13 \u2227 \ud835\udf12 ) ) \u22a2 ( \ud835\udf11 \u2192 \ud835\udf12 )",
            "step": 1,
            "theorem": "simprbi",
            "ground_truth": "simprbi \u22a2 ( [ y / x ] \ud835\udf11 \u2192 \u2203 x ( x = y \u2227 \ud835\udf11 ) )",
            "ground_truth_display": false,
            "statement_depth": 0,
            "_thrs_random_uniform": 0.67755,
            "_thrs_reconstruct": 1.0,
            "_thrs_obviousness": 1.0,
            "_thrs_weight": 1.0,
            "_thrs_complexity": 0.5,
            "_thrs_surprisingness": 0.5,
            "_thrs_intensity": 1.0,
            "_thrs_interestingness": 0.8,
            "_thrs_logistic_regression": 0.99923,
            "_thrs_random_forest": 0.675
        },
        {
            "number": 1736,
            "expression": "\u22a2 ( [ y / x ] \ud835\udf11 \u2194 ( ( x = y \u2192 \ud835\udf11 ) \u2227 \u2203 x ( x = y \u2227 \ud835\udf11 ) ) )",
            "prop_expression": " \u22a2 ( [ y / x ] \ud835\udf11 \u2194 ( ( x = y \u2192 \ud835\udf11 ) \u2227 \u2203 x ( x = y \u2227 \ud835\udf11 ) ) )",
            "step": 2,
            "theorem": "df-sb",
            "ground_truth": "df-sb \u22a2 ( [ y / x ] \ud835\udf11 \u2194 ( ( x = y \u2192 \ud835\udf11 ) \u2227 \u2203 x ( x = y \u2227 \ud835\udf11 ) ) )",
            "ground_truth_display": false,
            "statement_depth": 0,
            "_thrs_random_uniform": 0.69,
            "_thrs_reconstruct": 0.0,
            "_thrs_obviousness": 0.0,
            "_thrs_weight": 0.0,
            "_thrs_complexity": 0.5,
            "_thrs_surprisingness": 0.5,
            "_thrs_intensity": 0.0,
            "_thrs_interestingness": 0.2,
            "_thrs_logistic_regression": 0.71293,
            "_thrs_random_forest": 0.94
        }
    ],
    "is_train": false
}