{
    "theorem": "zfrep4",
    "hyps": [
        [
            1,
            2
        ],
        [
            1,
            6
        ],
        [
            2,
            3
        ],
        [
            3,
            4
        ],
        [
            4,
            5
        ],
        [
            6,
            7
        ],
        [
            7,
            8
        ],
        [
            7,
            14
        ],
        [
            8,
            9
        ],
        [
            8,
            10
        ],
        [
            8,
            11
        ],
        [
            11,
            12
        ],
        [
            11,
            13
        ],
        [
            14,
            15
        ]
    ],
    "expression": "{ y | \u2203 x ( \ud835\udf11 \u2227 \ud835\udf13 ) } \u2208 V",
    "steps": [
        {
            "expression": "\u22a2 { y | \u2203 x ( \ud835\udf11 \u2227 \ud835\udf13 ) } \u2208 V",
            "prop_expression": "A = B, A \u2208 C \u22a2 B \u2208 C",
            "step": 1,
            "theorem": "eqeltrri",
            "ground_truth": "eqeltrri \u22a2 { y | \u2203 x ( \ud835\udf11 \u2227 \ud835\udf13 ) } \u2208 V",
            "ground_truth_display": false,
            "statement_depth": 0,
            "_thrs_random_uniform": 0.256423617577782,
            "_thrs_reconstruct": 0.00042240062286293015,
            "_thrs_obviousness": 1.0,
            "_thrs_weight": 0.875,
            "_thrs_complexity": 0.0,
            "_thrs_surprisingness": 1.0,
            "_thrs_intensity": 0.9642857142857143,
            "_thrs_interestingness": 0.7678571428571429,
            "_thrs_logistic_regression": 0.9998375436071719,
            "_thrs_random_forest": 0.96
        },
        {
            "expression": "\u22a2 { y | \u2203 x ( x \u2208 { x | \ud835\udf11 } \u2227 \ud835\udf13 ) } = { y | \u2203 x ( \ud835\udf11 \u2227 \ud835\udf13 ) }",
            "prop_expression": "( \ud835\udf11 \u2194 \ud835\udf13 ) \u22a2 { x | \ud835\udf11 } = { x | \ud835\udf13 }",
            "step": 2,
            "theorem": "abbii",
            "ground_truth": "abbii \u22a2 { y | \u2203 x ( x \u2208 { x | \ud835\udf11 } \u2227 \ud835\udf13 ) } = { y | \u2203 x ( \ud835\udf11 \u2227 \ud835\udf13 ) }",
            "ground_truth_display": false,
            "statement_depth": 0,
            "_thrs_random_uniform": 0.282840948155481,
            "_thrs_reconstruct": 0.005315074922888323,
            "_thrs_obviousness": 0.005515814776062151,
            "_thrs_weight": 0.5625,
            "_thrs_complexity": 0.33333333333333337,
            "_thrs_surprisingness": 0.4787234042553192,
            "_thrs_intensity": 0.22159090909090912,
            "_thrs_interestingness": 0.32033269229112477,
            "_thrs_logistic_regression": 0.9711671078879357,
            "_thrs_random_forest": 0.975
        },
        {
            "expression": "\u22a2 ( \u2203 x ( x \u2208 { x | \ud835\udf11 } \u2227 \ud835\udf13 ) \u2194 \u2203 x ( \ud835\udf11 \u2227 \ud835\udf13 ) )",
            "prop_expression": "( \ud835\udf11 \u2194 \ud835\udf13 ) \u22a2 ( \u2203 x \ud835\udf11 \u2194 \u2203 x \ud835\udf13 )",
            "step": 3,
            "theorem": "exbii",
            "ground_truth": "exbii \u22a2 ( \u2203 x ( x \u2208 { x | \ud835\udf11 } \u2227 \ud835\udf13 ) \u2194 \u2203 x ( \ud835\udf11 \u2227 \ud835\udf13 ) )",
            "ground_truth_display": false,
            "statement_depth": 0,
            "_thrs_random_uniform": 0.40275798956656617,
            "_thrs_reconstruct": 0.00012936074038495592,
            "_thrs_obviousness": 0.00026288897553942915,
            "_thrs_weight": 0.6875,
            "_thrs_complexity": 0.6666666666666667,
            "_thrs_surprisingness": 0.4787234042553192,
            "_thrs_intensity": 0.14285714285714288,
            "_thrs_interestingness": 0.3952020205509336,
            "_thrs_logistic_regression": 0.8202556753427499,
            "_thrs_random_forest": 0.65
        },
        {
            "expression": "\u22a2 ( ( x \u2208 { x | \ud835\udf11 } \u2227 \ud835\udf13 ) \u2194 ( \ud835\udf11 \u2227 \ud835\udf13 ) )",
            "prop_expression": "( \ud835\udf11 \u2194 \ud835\udf13 ) \u22a2 ( ( \ud835\udf11 \u2227 \ud835\udf12 ) \u2194 ( \ud835\udf13 \u2227 \ud835\udf12 ) )",
            "step": 4,
            "theorem": "anbi1i",
            "ground_truth": "anbi1i \u22a2 ( ( x \u2208 { x | \ud835\udf11 } \u2227 \ud835\udf13 ) \u2194 ( \ud835\udf11 \u2227 \ud835\udf13 ) )",
            "ground_truth_display": false,
            "statement_depth": 0,
            "_thrs_random_uniform": 0.07794408630717942,
            "_thrs_reconstruct": 0.00012817368699146275,
            "_thrs_obviousness": 0.0001350405515706089,
            "_thrs_weight": 0.8125,
            "_thrs_complexity": 0.6666666666666667,
            "_thrs_surprisingness": 0.4787234042553192,
            "_thrs_intensity": 0.1989795918367347,
            "_thrs_interestingness": 0.4314009406620582,
            "_thrs_logistic_regression": 0.8743661400614766,
            "_thrs_random_forest": 0.66
        },
        {
            "expression": "\u22a2 ( x \u2208 { x | \ud835\udf11 } \u2194 \ud835\udf11 )",
            "prop_expression": " \u22a2 ( x \u2208 { x | \ud835\udf11 } \u2194 \ud835\udf11 )",
            "step": 5,
            "theorem": "abid",
            "ground_truth": "abid \u22a2 ( x \u2208 { x | \ud835\udf11 } \u2194 \ud835\udf11 )",
            "ground_truth_display": false,
            "statement_depth": 0,
            "_thrs_random_uniform": 0.1534180443755816,
            "_thrs_reconstruct": 8.464273885342068e-06,
            "_thrs_obviousness": 8.365300722721514e-06,
            "_thrs_weight": 0.9375,
            "_thrs_complexity": 1.0,
            "_thrs_surprisingness": 0.0,
            "_thrs_intensity": 0.08571428571428572,
            "_thrs_interestingness": 0.40464453020300173,
            "_thrs_logistic_regression": 0.5993786272205703,
            "_thrs_random_forest": 0.755
        },
        {
            "expression": "\u22a2 { y | \u2203 x ( x \u2208 { x | \ud835\udf11 } \u2227 \ud835\udf13 ) } \u2208 V",
            "prop_expression": "\u2203 x x = A \u22a2 A \u2208 V",
            "step": 6,
            "theorem": "issetri",
            "ground_truth": "issetri \u22a2 { y | \u2203 x ( x \u2208 { x | \ud835\udf11 } \u2227 \ud835\udf13 ) } \u2208 V",
            "ground_truth_display": false,
            "statement_depth": 0,
            "_thrs_random_uniform": 0.17580661389072472,
            "_thrs_reconstruct": 0.00041525423435414367,
            "_thrs_obviousness": 0.994066723142007,
            "_thrs_weight": 0.6875,
            "_thrs_complexity": 0.0,
            "_thrs_surprisingness": 1.0,
            "_thrs_intensity": 0.2142857142857143,
            "_thrs_interestingness": 0.5791704874855442,
            "_thrs_logistic_regression": 0.9890116024539701,
            "_thrs_random_forest": 0.98
        },
        {
            "expression": "\u22a2 \u2203 z z = { y | \u2203 x ( x \u2208 { x | \ud835\udf11 } \u2227 \ud835\udf13 ) }",
            "prop_expression": "\ud835\udf13, ( \ud835\udf11 \u2194 \ud835\udf13 ) \u22a2 \ud835\udf11",
            "step": 7,
            "theorem": "mpbir",
            "ground_truth": "mpbir \u22a2 \u2203 z z = { y | \u2203 x ( x \u2208 { x | \ud835\udf11 } \u2227 \ud835\udf13 ) }",
            "ground_truth_display": false,
            "statement_depth": 0,
            "_thrs_random_uniform": 0.9669093047605494,
            "_thrs_reconstruct": 1.0213534526806257e-06,
            "_thrs_obviousness": 0.9936563241904774,
            "_thrs_weight": 0.6875,
            "_thrs_complexity": 0.0,
            "_thrs_surprisingness": 0.4787234042553192,
            "_thrs_intensity": 1.0,
            "_thrs_interestingness": 0.6319759456891594,
            "_thrs_logistic_regression": 0.999920954219022,
            "_thrs_random_forest": 0.84
        },
        {
            "expression": "\u22a2 \u2203 z \u2200 y ( y \u2208 z \u2194 \u2203 x ( x \u2208 { x | \ud835\udf11 } \u2227 \ud835\udf13 ) )",
            "prop_expression": "( w \u2208 A \u2192 \u2200 x w \u2208 A ), A \u2208 V, ( x \u2208 A \u2192 \u2203 z \u2200 y ( \ud835\udf11 \u2192 y = z ) ) \u22a2 \u2203 z \u2200 y ( y \u2208 z \u2194 \u2203 x ( x \u2208 A \u2227 \ud835\udf11 ) )",
            "step": 8,
            "theorem": "zfrepclf",
            "ground_truth": "zfrepclf \u22a2 \u2203 z \u2200 y ( y \u2208 z \u2194 \u2203 x ( x \u2208 { x | \ud835\udf11 } \u2227 \ud835\udf13 ) )",
            "ground_truth_display": false,
            "statement_depth": 0,
            "_thrs_random_uniform": 0.14470836243925378,
            "_thrs_reconstruct": 1.0,
            "_thrs_obviousness": 0.9904028726845836,
            "_thrs_weight": 0.5625,
            "_thrs_complexity": 0.0,
            "_thrs_surprisingness": 0.4787234042553192,
            "_thrs_intensity": 0.4438775510204082,
            "_thrs_interestingness": 0.4951007655920622,
            "_thrs_logistic_regression": 0.998213682256657,
            "_thrs_random_forest": 0.78
        },
        {
            "expression": "\u22a2 ( y \u2208 { x | \ud835\udf11 } \u2192 \u2200 x y \u2208 { x | \ud835\udf11 } )",
            "prop_expression": " \u22a2 ( y \u2208 { x | \ud835\udf11 } \u2192 \u2200 x y \u2208 { x | \ud835\udf11 } )",
            "step": 9,
            "theorem": "hbab1",
            "ground_truth": "hbab1 \u22a2 ( y \u2208 { x | \ud835\udf11 } \u2192 \u2200 x y \u2208 { x | \ud835\udf11 } )",
            "ground_truth_display": false,
            "statement_depth": 0,
            "_thrs_random_uniform": 0.438157130787593,
            "_thrs_reconstruct": 0.0021121570887475474,
            "_thrs_obviousness": 0.0020874595340775854,
            "_thrs_weight": 0.6875,
            "_thrs_complexity": 0.6666666666666667,
            "_thrs_surprisingness": 0.0,
            "_thrs_intensity": 0.03571428571428571,
            "_thrs_interestingness": 0.27839368238300605,
            "_thrs_logistic_regression": 0.8303664804244867,
            "_thrs_random_forest": 0.74
        },
        {
            "expression": "\u22a2 { x | \ud835\udf11 } \u2208 V",
            "prop_expression": " \u22a2 { x | \ud835\udf11 } \u2208 V",
            "step": 10,
            "theorem": "zfrep4.1",
            "ground_truth": "zfrep4.1 \u22a2 { x | \ud835\udf11 } \u2208 V",
            "ground_truth_display": false,
            "statement_depth": 0,
            "_thrs_random_uniform": 0.17453896217682507,
            "_thrs_reconstruct": 0.0,
            "_thrs_obviousness": 0.0,
            "_thrs_weight": 1.0,
            "_thrs_complexity": 0.6666666666666667,
            "_thrs_surprisingness": 0.5212765957446809,
            "_thrs_intensity": 0.2142857142857143,
            "_thrs_interestingness": 0.4804457953394124,
            "_thrs_logistic_regression": 0.8950988369425336,
            "_thrs_random_forest": 0.9375
        },
        {
            "expression": "\u22a2 ( x \u2208 { x | \ud835\udf11 } \u2192 \u2203 z \u2200 y ( \ud835\udf13 \u2192 y = z ) )",
            "prop_expression": "( \ud835\udf11 \u2194 \ud835\udf13 ), ( \ud835\udf13 \u2192 \ud835\udf12 ) \u22a2 ( \ud835\udf11 \u2192 \ud835\udf12 )",
            "step": 11,
            "theorem": "sylbi",
            "ground_truth": "sylbi \u22a2 ( x \u2208 { x | \ud835\udf11 } \u2192 \u2203 z \u2200 y ( \ud835\udf13 \u2192 y = z ) )",
            "ground_truth_display": false,
            "statement_depth": 0,
            "_thrs_random_uniform": 0.25138219811112716,
            "_thrs_reconstruct": 9.56554593144997e-08,
            "_thrs_obviousness": 8.460447593979913e-06,
            "_thrs_weight": 0.6875,
            "_thrs_complexity": 0.0,
            "_thrs_surprisingness": 0.4787234042553192,
            "_thrs_intensity": 0.2857142857142857,
            "_thrs_interestingness": 0.29038923008343975,
            "_thrs_logistic_regression": 0.9965858471978746,
            "_thrs_random_forest": 0.77625
        },
        {
            "expression": "\u22a2 ( x \u2208 { x | \ud835\udf11 } \u2194 \ud835\udf11 )",
            "prop_expression": " \u22a2 ( x \u2208 { x | \ud835\udf11 } \u2194 \ud835\udf11 )",
            "step": 12,
            "theorem": "abid",
            "ground_truth": "abid \u22a2 ( x \u2208 { x | \ud835\udf11 } \u2194 \ud835\udf11 )",
            "ground_truth_display": false,
            "statement_depth": 0,
            "_thrs_random_uniform": 0.6115198085935705,
            "_thrs_reconstruct": 8.464273885342068e-06,
            "_thrs_obviousness": 8.365300722721514e-06,
            "_thrs_weight": 0.9375,
            "_thrs_complexity": 1.0,
            "_thrs_surprisingness": 0.0,
            "_thrs_intensity": 0.08571428571428572,
            "_thrs_interestingness": 0.40464453020300173,
            "_thrs_logistic_regression": 0.5993786272205703,
            "_thrs_random_forest": 0.725
        },
        {
            "expression": "\u22a2 ( \ud835\udf11 \u2192 \u2203 z \u2200 y ( \ud835\udf13 \u2192 y = z ) )",
            "prop_expression": " \u22a2 ( \ud835\udf11 \u2192 \u2203 z \u2200 y ( \ud835\udf13 \u2192 y = z ) )",
            "step": 13,
            "theorem": "zfrep4.2",
            "ground_truth": "zfrep4.2 \u22a2 ( \ud835\udf11 \u2192 \u2203 z \u2200 y ( \ud835\udf13 \u2192 y = z ) )",
            "ground_truth_display": false,
            "statement_depth": 0,
            "_thrs_random_uniform": 0.41970128863925726,
            "_thrs_reconstruct": 0.0,
            "_thrs_obviousness": 0.0,
            "_thrs_weight": 0.875,
            "_thrs_complexity": 0.6666666666666667,
            "_thrs_surprisingness": 0.15957446808510642,
            "_thrs_intensity": 0.10714285714285714,
            "_thrs_interestingness": 0.3616767983789261,
            "_thrs_logistic_regression": 0.8739671448710583,
            "_thrs_random_forest": 0.7678571428571428
        },
        {
            "expression": "\u22a2 ( \u2203 z z = { y | \u2203 x ( x \u2208 { x | \ud835\udf11 } \u2227 \ud835\udf13 ) } \u2194 \u2203 z \u2200 y ( y \u2208 z \u2194 \u2203 x ( x \u2208 { x | \ud835\udf11 } \u2227 \ud835\udf13 ) ) )",
            "prop_expression": "( \ud835\udf11 \u2194 \ud835\udf13 ) \u22a2 ( \u2203 x \ud835\udf11 \u2194 \u2203 x \ud835\udf13 )",
            "step": 14,
            "theorem": "exbii",
            "ground_truth": "exbii \u22a2 ( \u2203 z z = { y | \u2203 x ( x \u2208 { x | \ud835\udf11 } \u2227 \ud835\udf13 ) } \u2194 \u2203 z \u2200 y ( y \u2208 z \u2194 \u2203 x ( x \u2208 { x | \ud835\udf11 } \u2227 \ud835\udf13 ) ) )",
            "ground_truth_display": false,
            "statement_depth": 0,
            "_thrs_random_uniform": 0.7249621015729554,
            "_thrs_reconstruct": 0.00012936074038495592,
            "_thrs_obviousness": 0.0032524414852604577,
            "_thrs_weight": 0.0,
            "_thrs_complexity": 0.0,
            "_thrs_surprisingness": 0.4787234042553192,
            "_thrs_intensity": 0.18214285714285713,
            "_thrs_interestingness": 0.13282374057668736,
            "_thrs_logistic_regression": 0.9885878021068082,
            "_thrs_random_forest": 0.51
        },
        {
            "expression": "\u22a2 ( z = { y | \u2203 x ( x \u2208 { x | \ud835\udf11 } \u2227 \ud835\udf13 ) } \u2194 \u2200 y ( y \u2208 z \u2194 \u2203 x ( x \u2208 { x | \ud835\udf11 } \u2227 \ud835\udf13 ) ) )",
            "prop_expression": " \u22a2 ( A = { x | \ud835\udf11 } \u2194 \u2200 x ( x \u2208 A \u2194 \ud835\udf11 ) )",
            "step": 15,
            "theorem": "abeq2",
            "ground_truth": "abeq2 \u22a2 ( z = { y | \u2203 x ( x \u2208 { x | \ud835\udf11 } \u2227 \ud835\udf13 ) } \u2194 \u2200 y ( y \u2208 z \u2194 \u2203 x ( x \u2208 { x | \ud835\udf11 } \u2227 \ud835\udf13 ) ) )",
            "ground_truth_display": false,
            "statement_depth": 0,
            "_thrs_random_uniform": 0.09463705773524866,
            "_thrs_reconstruct": 0.0031615613505891513,
            "_thrs_obviousness": 0.0031245930612916373,
            "_thrs_weight": 0.125,
            "_thrs_complexity": 0.0,
            "_thrs_surprisingness": 0.4787234042553192,
            "_thrs_intensity": 0.0,
            "_thrs_interestingness": 0.12136959946332215,
            "_thrs_logistic_regression": 0.9733522152075581,
            "_thrs_random_forest": 0.46
        }
    ]
}